{
    "chapters": {
        "1": {
            "chapter": 1,
            "title": "道可道，非常道",
            "core_idea": "真正的「道」无法用语言完全描述。有些东西心里清清楚楚，但嘴巴说不出。这不是语言的失败，而是体验的深度——比语言更大的东西，需要亲自去感受。",
            "safety_notes": [
                "对低龄儿童避免使用「不可知论」或「虚无主义」的哲学表述",
                "不将「说不出来」曲解为「不需要学」或「不用思考」",
                "避免让孩子因为「说不清楚」而感到挫败——时刻强调「说不出来很正常」"
            ],
            "interaction_points": [
                {
                    "topic": "说不出来的东西",
                    "age_4_6": "用「最喜欢的味道」做比喻——能说出名字但说不出感觉。引导孩子发现生活中「只能感觉、说不出」的事物",
                    "age_7_9": "用「告诉外星人什么是红色」做思想实验，让孩子亲身体验语言的局限",
                    "age_10_12": "探讨语言和体验的关系——为什么拥抱的感觉说出来就不是那个感觉了？引入「道」的超越性"
                },
                {
                    "topic": "语言之外的理解",
                    "age_4_6": null,
                    "age_7_9": "引导孩子回忆：有什么事情不需要说出来，爸爸妈妈就知道的？感受「心照不宣」的美好",
                    "age_10_12": "探讨一个悖论：既然「道」说不出来，老子为什么写了五千字？他在做什么？"
                }
            ],
            "parent_tips": "这个章节的核心是让孩子感受到「有些事情不需要说出来也能被理解」。在共读之外，今天可以试着多给孩子一些「不用说出口」的理解——比如 ta 累了的时候，不问「你怎么了」，只是给 ta 一杯水。",
            "review_status": "approved",
            "reviewed_by": "",
            "reviewed_at": "2026-05-12",
            "review_history": [
                {
                    "action": "created",
                    "by": "extract_meta.py",
                    "at": "2026-05-11T00:00:00Z",
                    "notes": "AI generated"
                },
                {
                    "action": "approved",
                    "by": "产品经理",
                    "at": "2026-05-11T00:00:00Z",
                    "notes": "Initial review"
                }
            ]
        },
        "2": {
            "chapter": 2,
            "title": "天下皆知美之为美",
            "core_idea": "美和丑、高和矮、长和短——这些对立的词其实是互相定义的。没有「矮」就没有「高」，没有「难过」就感受不到「开心」。万物的差异不是缺陷，而是世界的丰富性。",
            "safety_notes": [
                "避免将「对立统一」简化为「好坏都一样」的相对主义",
                "不涉及外貌、身材等可能引发儿童身体焦虑的外在比较",
                "对低龄儿童不引入「善恶」「是非」等可能引起道德困惑的二元对立话题",
                "不使用「没有丑就没有美」这种可能让某些孩子感到被贴标签的表达"
            ],
            "interaction_points": [
                {
                    "topic": "一对好朋友",
                    "age_4_6": "引导孩子发现「高和矮」「大和小」这些词像好朋友一样互相离不开对方。和孩子比赛找更多的「好朋友」词对",
                    "age_7_9": "引导孩子推理：如果世界上所有人一样高，「高」这个词还存在吗？理解对立概念的相互依存关系",
                    "age_10_12": "探讨「有无相生，难易相成」的深层含义——困难和容易、失败和成功之间的关系"
                },
                {
                    "topic": "不一样才有趣",
                    "age_4_6": null,
                    "age_7_9": "引导孩子思考：如果从没哭过，还会觉得笑很特别吗？分享自己的「因为难过过，才更珍惜开心」的经历",
                    "age_10_12": "探讨：如果全班同学都和你一模一样——会怎样？引导孩子珍视「不一样」的价值"
                }
            ],
            "parent_tips": "这个章节是一个绝佳的「接纳差异」的教育契机。如果孩子在学校遇到了「和别人不一样」的困扰，可以用老子的话告诉 ta：「天下皆知美之为美，斯恶已」——正因为有不一样，世界才有趣。你不需要和别人一样。",
            "review_status": "approved",
            "reviewed_by": "产品经理",
            "reviewed_at": "2026-05-11",
            "review_history": [
                {
                    "action": "created",
                    "by": "extract_meta.py",
                    "at": "2026-05-11T00:00:00Z",
                    "notes": "AI generated"
                },
                {
                    "action": "approved",
                    "by": "产品经理",
                    "at": "2026-05-11T00:00:00Z",
                    "notes": "Initial review"
                }
            ]
        },
        "3": {
            "chapter": 3,
            "title": "不尚贤",
            "core_idea": "不总说谁最棒，不总说哪个东西最珍贵，不总展示让人眼红的东西，大家就不会争来争去、想偷想抢、心里乱糟糟。肚子吃饱、心里安稳、身体棒棒，生活就自然好了。",
            "safety_notes": [
                "避免将'不争'理解为消极退缩或放弃努力，要强调是减少不必要的比较和攀比",
                "避免将'无知无欲'理解为反对学习知识或追求理想，要解释为不被杂念干扰",
                "避免用'偷盗'等负面行为直接指责孩子，而是用故事引导理解"
            ],
            "interaction_points": [
                {
                    "topic": "小动物不争",
                    "age_4_6": "宝宝，你看小猫咪和小狗一起玩，它们有没有抢着当'最棒的小动物'？它们只是开心地追尾巴。你能学小猫叫一声吗？",
                    "age_7_9": "如果森林里的小动物都争着当'最厉害'，会发生什么？你觉得它们不争的时候，是不是更快乐？",
                    "age_10_12": "老子说'不尚贤'，就像森林里没有'最棒动物'的比赛，每个动物都有自己的特点。你觉得自己有什么独特的地方，不需要和别人比？"
                },
                {
                    "topic": "好东西不炫耀",
                    "age_4_6": "妈妈有一个漂亮的发卡，如果一直拿在手里晃，你会不会也想抢？我们把它放在盒子里，大家都不看，是不是就不想抢了？",
                    "age_7_9": "如果学校里有同学总炫耀一个新玩具，你会不会也想要？老子说，不把东西说得特别珍贵，大家就不会想去偷。你觉得对吗？",
                    "age_10_12": "广告里常说'这个最棒'，老子说'不贵难得之货'。你发现广告在做什么了吗？我们怎么不被它牵着走？"
                },
                {
                    "topic": "把智慧带入生活",
                    "age_4_6": "吃饭时，宝宝可以专心吃，不用看别人碗里有什么。吃饱了，摸摸肚子，开心地笑一笑。",
                    "age_7_9": "和家人聊聊：家里有没有什么东西，我们觉得特别珍贵，反而让我们不开心？我们可以试试不那么在意它。",
                    "age_10_12": "这一章的道理很深，不急着全懂。以后遇到'比较'的时候，可以想起老子说的'不尚贤'，慢慢体会。"
                }
            ],
            "parent_tips": "和孩子一起读时，就像在讲一个有趣的寓言。不用急着解释，让孩子先感受故事里的画面。你放松了，孩子也会放松。",
            "review_status": "approved",
            "reviewed_by": "",
            "reviewed_at": "2026-05-12",
            "review_history": [
                {
                    "action": "created",
                    "by": "extract_meta.py",
                    "at": "2026-05-12T00:00:00Z",
                    "notes": "AI generated - awaiting review"
                },
                {
                    "action": "reviewing",
                    "by": "admin",
                    "at": "2026-05-12T09:21:23.265Z",
                    "notes": ""
                },
                {
                    "action": "approved",
                    "by": "admin",
                    "at": "2026-05-12T09:21:40.977Z",
                    "notes": "何继杰"
                }
            ]
        },
        "7": {
            "chapter": 7,
            "title": "天长地久",
            "core_idea": "你看天和地，它们不为自己忙活，却一直存在。学它们的样，不争不抢，反而能活得更好。",
            "safety_notes": [
                "避免将「无私」解释为否定自我价值，要强调孩子爱自己也是好的",
                "避免用「不争」来批评孩子争取玩具或表现的行为",
                "避免让孩子误解为「不保护自己」是危险的"
            ],
            "interaction_points": [
                {
                    "topic": "天和地像什么",
                    "age_4_6": "让孩子指指天空和大地，问：天是不是一直在头顶？地是不是一直在脚下？它们像不像一个永远陪着你的大朋友？",
                    "age_7_9": "问孩子：天和地为什么能一直存在？因为它们不为自己忙活。你觉得它们为谁忙活呢？比如天给我们阳光，地给我们花草。",
                    "age_10_12": "问孩子：老子说天地不自生，所以长生。你怎么理解「不自生」？可以举例说说天地是怎么为万物服务的吗？"
                },
                {
                    "topic": "不抢反而先",
                    "age_4_6": "玩排队游戏：让孩子站在后面，然后说「我们让前面的小朋友先走」，结果大家反而让你先走。体验一下不抢的感觉。",
                    "age_7_9": "问孩子：在班里，如果大家都抢着当班长，可能会吵架。如果一个人不抢，但很热心帮助大家，大家会不会更愿意选他？为什么？",
                    "age_10_12": "讨论：老子说「后其身而身先」，你觉得生活中哪些例子符合这个道理？比如团队合作中，不抢功的人反而更受尊重。你怎么看？"
                },
                {
                    "topic": "把智慧带入生活",
                    "age_4_6": "吃饭时，让孩子先帮家人摆碗筷，不抢着吃第一口，然后问：先帮别人，自己是不是更开心？",
                    "age_7_9": "邀请孩子和父母聊聊：家里有没有谁「不为自己忙活」却让全家更幸福的事？比如妈妈做饭，爸爸修东西。",
                    "age_10_12": "提醒孩子：本章的智慧可以慢慢体会，不急于做到完美。下次遇到想争的时候，想想天和地，也许会有不同的选择。"
                }
            ],
            "parent_tips": "和孩子一起看看天空和大地吧，不用讲道理，只是静静地感受。",
            "review_status": "approved",
            "reviewed_by": "",
            "reviewed_at": "2026-05-12",
            "review_history": [
                {
                    "action": "created",
                    "by": "extract_meta.py",
                    "at": "2026-05-12T00:00:00Z",
                    "notes": "AI generated - awaiting review"
                },
                {
                    "action": "reviewing",
                    "by": "admin",
                    "at": "2026-05-12T08:56:49.043Z",
                    "notes": ""
                },
                {
                    "action": "approved",
                    "by": "admin",
                    "at": "2026-05-12T08:58:00.213Z",
                    "notes": ""
                }
            ]
        },
        "8": {
            "chapter": 8,
            "title": "上善若水",
            "core_idea": "最高的善像水一样，利万物而不争。水往低处流、柔能克刚——真正的力量不是争夺，而是柔软地滋养一切。",
            "safety_notes": [
                "避免使用「水能载舟亦能覆舟」等暗含危险或权力隐喻的比喻",
                "不涉及洪水、溺水、海啸等可能引发儿童恐惧的自然灾害话题",
                "不将「不争」曲解为消极逃避或放弃努力"
            ],
            "interaction_points": [
                {
                    "topic": "水的厉害之处",
                    "age_4_6": "引导孩子发现水的各种形态变化（冰、汽、雨），用拟人化方式感受水的「性格」——柔软但能找到任何路",
                    "age_7_9": "引导孩子思考水「利万物而不争」的含义，联系生活中默默付出的人和事",
                    "age_10_12": "探讨「不争」的哲学含义——不争是否等于输？引导思辨而非给出标准答案"
                },
                {
                    "topic": "柔软的力量",
                    "age_4_6": null,
                    "age_7_9": "引导孩子发现「柔能克刚」的实例——看起来很软但其实很厉害的东西或人",
                    "age_10_12": "探讨「天下之至柔，驰骋天下之至坚」的含义，联系现实中的「软实力」"
                },
                {
                    "topic": "把智慧带入生活",
                    "age_4_6": "引导孩子在洗澡时和水「做朋友」，分享开心的事",
                    "age_7_9": "邀请孩子和父母聊聊：我们家谁像「水」？",
                    "age_10_12": "提醒孩子：这章的深意可以慢慢聊，不急于求成"
                }
            ],
            "parent_tips": "和孩子聊「不争」的时候，不用刻意讲道理。问问 ta：「今天有没有和同学争玩具？」让 ta 自己说。你只负责听。孩子说出自己的经历时，不评判、不纠正，只是点头和微笑。",
            "review_status": "approved",
            "reviewed_by": "产品经理",
            "reviewed_at": "2026-05-11",
            "review_history": [
                {
                    "action": "created",
                    "by": "extract_meta.py",
                    "at": "2026-05-11T00:00:00Z",
                    "notes": "AI generated"
                },
                {
                    "action": "approved",
                    "by": "产品经理",
                    "at": "2026-05-11T00:00:00Z",
                    "notes": "Initial review"
                }
            ]
        },
        "9": {
            "chapter": 9,
            "title": "持而盈之不如其已",
            "core_idea": "就像杯子里的水，倒得太满就会洒出来。我们不需要事事都追求最满、最好，懂得适可而止，反而能拥有更多的快乐和安全。",
            "safety_notes": [
                "避免用‘你太贪心’来评价孩子，而是说‘我们可以试试少拿一点’。",
                "避免用‘东西太多会招小偷’吓唬孩子，而是说‘东西够用就好，多了反而不好收拾’。",
                "避免将‘功遂身退’解释为‘做得好就要赶紧逃跑’，而是说‘完成一件事后，可以休息一下，把机会让给别人’。"
            ],
            "interaction_points": [
                {
                    "topic": "端水小实验",
                    "age_4_6": "让孩子端一杯水慢慢走，看看水洒出来没有。然后换成半杯水再走一遍，说说哪次更容易。",
                    "age_7_9": "问问孩子：如果杯子里的水太满，走路时会怎样？生活中有什么事情也是‘太满了反而不好’？",
                    "age_10_12": "和孩子讨论：为什么老子说‘持而盈之不如其已’？你能想到哪些‘过犹不及’的例子？"
                },
                {
                    "topic": "玩玩具的学问",
                    "age_4_6": "拿出几个玩具，问孩子：如果所有玩具都堆在一起，你还能好好玩吗？试试一次只玩一个，是不是更开心？",
                    "age_7_9": "让孩子回忆：上次把所有玩具都拿出来，是不是很快就觉得乱、不想玩了？如果只选最喜欢的几个玩，感觉有什么不同？",
                    "age_10_12": "讨论‘金玉满堂，莫之能守’：为什么东西越多越难守住？我们真的需要那么多东西才能快乐吗？"
                },
                {
                    "topic": "把智慧带入生活",
                    "age_4_6": "洗澡时，和孩子一起往杯子里倒水，试试倒多少刚好不洒出来，告诉孩子‘刚刚好就是最好’。",
                    "age_7_9": "邀请孩子聊聊：家里有没有什么东西太多了，反而让人烦恼？比如书太多、衣服太多？我们可以怎么处理？",
                    "age_10_12": "提醒孩子：老子说的‘功遂身退’不是让你放弃努力，而是让你懂得在适当的时候停下来，欣赏自己的成果。"
                }
            ],
            "parent_tips": "和孩子一起玩‘刚刚好’的游戏吧，比如盛饭、倒水、挑选玩具，让‘知足’变成一种轻松的体验。",
            "review_status": "approved",
            "reviewed_by": "",
            "reviewed_at": "2026-05-12",
            "review_history": [
                {
                    "action": "created",
                    "by": "extract_meta.py",
                    "at": "2026-05-12T00:00:00Z",
                    "notes": "AI generated - awaiting review"
                },
                {
                    "action": "reviewing",
                    "by": "admin",
                    "at": "2026-05-12T08:58:19.776Z",
                    "notes": ""
                },
                {
                    "action": "approved",
                    "by": "admin",
                    "at": "2026-05-12T08:59:28.772Z",
                    "notes": ""
                }
            ]
        },
        "10": {
            "chapter": 10,
            "title": "载营魄抱一",
            "core_idea": "这一章像一位智慧的老爷爷在问我们六个有趣的问题，提醒我们：做最好的自己，不是要拼命做什么，而是学会让心静下来、身体放松、像小婴儿一样柔软，并且帮助别人时不控制别人。",
            "safety_notes": [
                "避免讨论“灵魂出窍”等超自然概念，以免引起儿童恐惧。",
                "不要将“像婴儿一样”曲解为要幼稚或退步，应强调纯真和柔软。",
                "避免将“无为”解释为什么都不做，而是不强行控制。",
                "不涉及任何关于死亡、疾病或灾难的比喻。"
            ],
            "interaction_points": [
                {
                    "topic": "心和身体在一起",
                    "age_4_6": "可以问孩子：'宝宝，你现在玩玩具的时候，小脑袋有没有想着别的事呀？我们试试看，手在搭积木，心也在搭积木，像小猫咪专心舔爪子一样。'",
                    "age_7_9": "可以问孩子：'你什么时候会觉得自己的身体在做一件事，心里却在想另一件事？比如吃饭时想着动画片？那种感觉怎么样？我们试试吃饭时只感受米饭的味道。'",
                    "age_10_12": "可以问孩子：'老子问“能无离乎”，意思是身心合一。你觉得自己在什么时候最容易分心？有没有什么方法让自己回到当下？比如深呼吸或者专注做一件事。'"
                },
                {
                    "topic": "像婴儿一样柔软",
                    "age_4_6": "可以问孩子：'小婴儿的手脚软软的，你学学小婴儿伸个懒腰？我们像小猫咪一样放松，全身软软的，是不是很舒服？'",
                    "age_7_9": "可以问孩子：'你觉得柔软和坚强哪个更好？比如小草很软，但风来了不会断；石头很硬，但摔一下可能就裂了。你什么时候可以像小草一样柔软？'",
                    "age_10_12": "可以问孩子：'老子说“专气致柔，能婴儿乎”，你觉得婴儿的状态有什么特别？我们长大以后，还能不能保持那种柔软和开放？比如遇到困难时不硬扛，而是灵活应对。'"
                },
                {
                    "topic": "把智慧带入生活",
                    "age_4_6": "洗澡时，可以跟孩子说：'我们像小鸭子一样让水轻轻流过身体，放松一下，感受水和皮肤的接触，就像老子爷爷说的心在身体里一样。'",
                    "age_7_9": "可以邀请孩子：'今天晚饭时，我们每个人都说说自己什么时候最放松、最像小婴儿一样柔软？比如妈妈泡杯茶的时候，爸爸看书的时侯。'",
                    "age_10_12": "可以提醒孩子：'老子说的智慧不是一次就能懂的，我们可以在生活中慢慢体会。比如下次你生气时，试试先深呼吸，让自己柔软下来，看看会怎样。'"
                }
            ],
            "parent_tips": "亲爱的家长，这一章不需要孩子完全理解，只要在生活里一起感受那份柔软和专注就好。你放松的样子，就是孩子最好的榜样。",
            "review_status": "approved",
            "reviewed_by": "何继杰",
            "reviewed_at": "2026-05-13",
            "review_history": [
                {
                    "action": "reviewing",
                    "by": "admin",
                    "at": "2026-05-13T11:32:17.426Z",
                    "notes": ""
                },
                {
                    "action": "approved",
                    "by": "何继杰",
                    "at": "2026-05-13T11:32:46Z",
                    "notes": "批量2 Article 11安全检查通过"
                }
            ]
        },
        "11": {
            "chapter": 11,
            "title": "三十辐共一毂",
            "core_idea": "看得见的东西给我们方便，但看不见的“空”才是让东西真正好用的秘密。就像杯子能装水是因为中间是空的，房子能住人是因为里面有空间。",
            "safety_notes": [
                "避免用“空就是没有”的说法，以免孩子感到害怕或困惑",
                "不要将“无”与“一无所有”或“空虚”联系起来，以免引发负面联想",
                "避免讨论“空比实更重要”的争议，强调“有和空是一对好搭档”"
            ],
            "interaction_points": [
                {
                    "topic": "找找空的地方",
                    "age_4_6": "和孩子一起找家里的“空”：杯子里的空、书包里的空、房间角落的空。让孩子用手指一指，说“这里空空的，可以装东西！”",
                    "age_7_9": "问孩子：如果碗是实心的，能盛汤吗？如果房子没有窗户和门，能住人吗？让孩子用家里的物品举例，说说“空”有什么用。",
                    "age_10_12": "引导孩子思考：除了物体，生活中还有哪些“空”很重要？比如时间表里的空闲、书包里的空位。讨论“空”是不是一种资源。"
                },
                {
                    "topic": "看不见的本领",
                    "age_4_6": "让孩子想想：风看不见，但能吹动树叶；声音看不见，但能听见。一起学风吹树叶的声音“沙沙沙”，感受看不见的东西。",
                    "age_7_9": "问孩子：你觉得还有哪些看不见的东西很有用？比如爱、想法、空气。让孩子画一个“看不见的本领”画，比如画一个爱心代表爱。",
                    "age_10_12": "讨论：古人说“无之以为用”，现代生活中有没有类似例子？比如Wi-Fi信号看不见，但能让手机上网。鼓励孩子举出更多例子。"
                },
                {
                    "topic": "把智慧带入生活",
                    "age_4_6": "洗澡时，让孩子观察浴缸里的水：水占满了浴缸，但宝宝的身体进去后，水就溢出来了——因为身体占了“空”。",
                    "age_7_9": "邀请孩子和父母聊聊：家里哪些东西是“空”的？比如储物箱、冰箱、铅笔盒。一起整理一个“空”的空间，比如腾出一个抽屉放玩具。",
                    "age_10_12": "提醒孩子：这一章的智慧可以慢慢体会，比如学习时留出空白时间思考，比一直做题更有用。不急于求成，空和实要平衡。"
                }
            ],
            "parent_tips": "和孩子一起发现生活中的“空”吧，就像发现宝藏一样。不必刻意解释，只需在玩的时候轻轻点出：看，这里空空的，真有用呢。",
            "review_status": "approved",
            "reviewed_by": "",
            "reviewed_at": "2026-05-12",
            "review_history": [
                {
                    "action": "created",
                    "by": "extract_meta.py",
                    "at": "2026-05-12T00:00:00Z",
                    "notes": "AI generated - awaiting review"
                },
                {
                    "action": "reviewing",
                    "by": "admin",
                    "at": "2026-05-12T10:36:12.226Z",
                    "notes": ""
                },
                {
                    "action": "approved",
                    "by": "admin",
                    "at": "2026-05-12T10:36:57.834Z",
                    "notes": "何继杰"
                }
            ]
        },
        "12": {
            "chapter": 12,
            "title": "五色令人目盲",
            "core_idea": "就像吃太多零食会尝不出饭菜的香味，眼睛看太多花花绿绿，心里反而空空的。真正舒服的感觉，来自简单和安静。",
            "safety_notes": [
                "避免让孩子觉得看动画片、吃零食是完全错误的",
                "不要用‘你总是……’指责孩子追求感官刺激的行为",
                "避免将‘花花绿绿’与‘坏’直接等同，以免孩子产生恐惧"
            ],
            "interaction_points": [
                {
                    "topic": "眼睛的旅行",
                    "age_4_6": "让孩子闭上眼睛，听一听周围的声音，然后睁开眼指一指最安静的东西是什么。可以学小猫走路，感受安静。",
                    "age_7_9": "和孩子一起数一数家里有多少种颜色，然后问：如果只有一种颜色，你会觉得怎样？",
                    "age_10_12": "讨论：为什么老子说‘五色令人目盲’？是不是所有颜色都不好吗？还是太多了会让人看不清重要的东西？"
                },
                {
                    "topic": "零食大作战",
                    "age_4_6": "让孩子摸摸肚子，问：肚子饿的时候，吃什么最香？然后假装小兔子吃胡萝卜，感受简单食物的味道。",
                    "age_7_9": "和孩子聊聊：如果一直吃零食，会有什么感觉？妈妈做的饭和零食有什么不同？",
                    "age_10_12": "引导思考：老子说‘为腹不为目’，是不是在说我们不需要任何好看的东西？还是提醒我们不要被表面的诱惑带走？"
                },
                {
                    "topic": "把智慧带入生活",
                    "age_4_6": "洗澡时，和孩子一起安静地玩一会儿水，感受水流过手心的感觉，不急着玩玩具。",
                    "age_7_9": "邀请孩子和父母一起整理玩具，把最喜欢的几件留下，其他的收起来，体验‘少一点’的快乐。",
                    "age_10_12": "提醒孩子：这一章的智慧可以慢慢体会，下次觉得眼花缭乱时，可以试试闭上眼睛，感受内心的安静。"
                }
            ],
            "parent_tips": "和孩子一起感受简单的小确幸，比如一起看一朵云、听一阵风，不用刻意说教，陪伴本身就是最好的传递。",
            "review_status": "approved",
            "reviewed_by": "",
            "reviewed_at": "2026-05-12",
            "review_history": [
                {
                    "action": "created",
                    "by": "extract_meta.py",
                    "at": "2026-05-12T00:00:00Z",
                    "notes": "AI generated - awaiting review"
                },
                {
                    "action": "reviewing",
                    "by": "admin",
                    "at": "2026-05-12T10:37:26.253Z",
                    "notes": ""
                },
                {
                    "action": "approved",
                    "by": "admin",
                    "at": "2026-05-12T10:37:48.338Z",
                    "notes": "何继杰"
                }
            ]
        },
        "14": {
            "chapter": 14,
            "title": "视之不见名曰夷",
            "core_idea": "世界上最重要的东西常常是看不见的，比如爱、信任、规律，它们就像空气一样，虽然摸不着，但却真实存在，而且让一切运转起来。",
            "safety_notes": [
                "避免用'看不见的东西'暗示有鬼怪或可怕的事物存在。",
                "避免说'道是虚无的'，以免让孩子觉得一切都不重要。",
                "避免讨论'看不见的力量'时联系到超自然或恐惧元素。"
            ],
            "interaction_points": [
                {
                    "topic": "看不见的朋友",
                    "age_4_6": "引导孩子想想：风看不见，但你能感觉到它吗？可以一起用手扇风，或者吹动头发，感受风的存在。",
                    "age_7_9": "问孩子：你觉得爱看得见吗？那你怎么知道爸爸妈妈爱你？让孩子举例说明爱是如何被感受到的。",
                    "age_10_12": "邀请孩子思考：除了爱，还有哪些重要的东西是看不见的？比如信任、规则、时间。它们怎样影响着我们的生活？"
                },
                {
                    "topic": "最远有多远",
                    "age_4_6": "和孩子一起看天空，问：你能看到天空的尽头吗？那远处有什么？引导孩子感受'看不到头'的概念。",
                    "age_7_9": "问孩子：如果一直往前走，能走到世界的尽头吗？为什么？引导孩子理解'没有开头也没有结尾'。",
                    "age_10_12": "讨论：老子说'迎之不见其首，随之不见其后'，你觉得什么东西是这样的？比如时间、数字、宇宙。"
                },
                {
                    "topic": "把智慧带入生活",
                    "age_4_6": "洗澡时，让孩子把手伸进水里，问：你能抓住水吗？水虽然抓不住，但能感觉到它。就像爱一样。",
                    "age_7_9": "吃饭时，问孩子：你觉得食物的味道看得见吗？那你怎么知道它好吃？引导孩子感受看不见的体验。",
                    "age_10_12": "提醒孩子：本章的智慧可以慢慢体会，就像空气一样，它一直都在，不用着急一下子明白。"
                }
            ],
            "parent_tips": "和孩子一起闭上眼睛，感受一下周围的空气，或者彼此拥抱，体会那种看不见但真实存在的温暖。",
            "review_status": "approved",
            "reviewed_by": "",
            "reviewed_at": "2026-05-12",
            "review_history": [
                {
                    "action": "created",
                    "by": "extract_meta.py",
                    "at": "2026-05-12T00:00:00Z",
                    "notes": "AI generated - awaiting review"
                },
                {
                    "action": "reviewing",
                    "by": "admin",
                    "at": "2026-05-12T10:37:56.642Z",
                    "notes": ""
                },
                {
                    "action": "approved",
                    "by": "admin",
                    "at": "2026-05-12T10:38:30.766Z",
                    "notes": "何继杰"
                }
            ]
        },
        "16": {
            "chapter": 16,
            "title": "致虚极守静笃",
            "core_idea": "就像湖水安静下来才能看清水底一样，我们让心静下来，就能发现万物都会回到自己的根，就像树叶落下变成养分回到树根。懂得这个道理，心里就会宽广，做事也公正，生活自然平安长久。",
            "safety_notes": [
                "避免将'归根'解释为死亡或消失，应强调循环与新生，如树叶变养分滋养新叶。",
                "避免将'静'描述为绝对不动或压抑，而是像湖水一样清澈宁静。",
                "避免将'知常'与'妄作'对比时，用'做错事会倒霉'来恐吓孩子，应强调理解规律带来安心。"
            ],
            "interaction_points": [
                {
                    "topic": "万物归根",
                    "age_4_6": "和宝宝一起看窗外的树叶，捡一片落叶，说：'看，树叶宝宝离开了大树妈妈，落到地上，变成泥土，又去喂大树妈妈了。' 然后让孩子也找一片落叶，一起说'回家啦'。",
                    "age_7_9": "问孩子：'你养过植物吗？如果叶子黄了掉下来，你觉得它去哪里了？' 引导孩子思考物质循环，比如苹果核埋土里变成养分。",
                    "age_10_12": "问孩子：'老子说万物都会回到自己的根，你觉得人的'根'是什么？是家？还是大自然？' 鼓励孩子结合生活经验讨论。"
                },
                {
                    "topic": "安静的力量",
                    "age_4_6": "玩'安静小湖'游戏：让孩子像湖水一样安静坐好，听一听周围的声音（鸟叫、钟声），然后说说听到了什么。",
                    "age_7_9": "问孩子：'你什么时候觉得心里很安静？是画画时？还是听故事时？安静的时候，你有什么新发现？'",
                    "age_10_12": "讨论：'老子说'致虚极，守静笃'，你觉得在现代生活中，我们怎么才能让心静下来？比如写作业前先深呼吸？'"
                },
                {
                    "topic": "把智慧带入生活",
                    "age_4_6": "洗澡时，和孩子一起看水中的泡泡慢慢消失，说：'泡泡也回家了，变成水啦。'",
                    "age_7_9": "邀请孩子和父母聊聊：'我们家里有没有什么东西是循环使用的？比如废纸回收、厨余堆肥？'",
                    "age_10_12": "提醒孩子：'这一章的智慧可以慢慢体会，就像种子发芽需要时间。下次遇到烦心事，先静一静，看看事情会怎么变化。'"
                }
            ],
            "parent_tips": "共读后，不妨和孩子一起静静地看一棵树、一片云，享受安静的陪伴，让智慧在无声中流淌。",
            "review_status": "approved",
            "reviewed_by": "",
            "reviewed_at": "2026-05-12",
            "review_history": [
                {
                    "action": "created",
                    "by": "extract_meta.py",
                    "at": "2026-05-12T00:00:00Z",
                    "notes": "AI generated - awaiting review"
                },
                {
                    "action": "reviewing",
                    "by": "admin",
                    "at": "2026-05-12T10:38:41.126Z",
                    "notes": ""
                },
                {
                    "action": "approved",
                    "by": "admin",
                    "at": "2026-05-12T10:39:10.298Z",
                    "notes": "何继杰"
                }
            ]
        },
        "22": {
            "chapter": 22,
            "title": "曲则全",
            "core_idea": "有时候，弯下腰、让一让，反而能得到更多。就像小树苗在风里弯腰就不会折断，水往低处流却汇成了大海。",
            "safety_notes": [
                "避免将“不争”解释为软弱或放弃，要强调是自然顺势、不强行对抗。",
                "避免用“假装弱小”来解读，以免孩子误解为耍心机。",
                "避免讨论竞争中的输赢，而是关注合作与成长。"
            ],
            "interaction_points": [
                {
                    "topic": "弯腰的树",
                    "age_4_6": "带孩子看窗外的树，问：“你看风来的时候，树枝会怎么样？”让孩子模仿树枝弯腰的样子，然后说：“树枝弯一弯，就不会断，真聪明！”",
                    "age_7_9": "和孩子一起观察一棵在风中的树，讨论：“为什么弯下腰的树不容易断？如果是硬撑着不弯，会怎样？”引导孩子联系自己生活中“让一让”的经历。",
                    "age_10_12": "引导孩子思考：“老子说‘曲则全’，你觉得除了树，还有什么例子？比如在排队时，或者和同学意见不同时，让步是不是反而让事情更顺利？”"
                },
                {
                    "topic": "水的秘密",
                    "age_4_6": "洗澡时玩水，用小杯子倒水到低处，说：“水宝宝喜欢去低洼的地方，你看它们聚在一起，变多了！”",
                    "age_7_9": "问孩子：“如果你在沙滩上挖一个坑，海水会怎么样？”引导孩子理解“洼则盈”——低的地方能容纳更多水。联系生活中“谦虚”的人更容易学到东西。",
                    "age_10_12": "和孩子讨论：“老子说水往低处流，但水却很有力量。你觉得‘不争’和‘强大’矛盾吗？为什么？”"
                },
                {
                    "topic": "把智慧带入生活",
                    "age_4_6": "和孩子玩“让一让”游戏：走路时故意挤一下，然后说“我们让一让，一起走”，让孩子体验让步后的顺畅。",
                    "age_7_9": "请孩子回想一天中是否有“让一让”的时刻，比如让弟弟先玩玩具、排队时不插队。聊聊当时的感觉。",
                    "age_10_12": "提醒孩子：老子的智慧需要慢慢体会，就像小树慢慢长大。今天聊的“曲则全”，可以在以后遇到困难时再想起。"
                }
            ],
            "parent_tips": "和孩子一起观察自然，比如风吹草动、水流石转，这些日常中藏着老子的智慧。不用急着讲道理，多让孩子自己发现就好。",
            "review_status": "approved",
            "reviewed_by": "",
            "reviewed_at": "2026-05-12",
            "review_history": [
                {
                    "action": "created",
                    "by": "extract_meta.py",
                    "at": "2026-05-12T00:00:00Z",
                    "notes": "AI generated - awaiting review"
                },
                {
                    "action": "reviewing",
                    "by": "admin",
                    "at": "2026-05-12T10:39:18.386Z",
                    "notes": ""
                },
                {
                    "action": "approved",
                    "by": "admin",
                    "at": "2026-05-12T10:39:51.702Z",
                    "notes": "何继杰"
                }
            ]
        },
        "24": {
            "chapter": 24,
            "title": "企者不立",
            "core_idea": "有时候越着急越想表现，反而做不好事情。就像小树慢慢长才能又高又壮，我们慢慢来，踏实做，反而更棒。",
            "safety_notes": [
                "避免说‘你这样做就是自夸’，应换成‘我们试试不着急，慢慢来’",
                "避免用‘丑’‘讨厌’形容行为，应说‘这样可能让别人不舒服’",
                "避免将‘不争’误解为‘不努力’，强调‘踏实努力’和‘不炫耀’的区别"
            ],
            "interaction_points": [
                {
                    "topic": "小树慢慢长",
                    "age_4_6": "和孩子一起看一棵小树或盆栽，用手比划‘踮脚尖’和‘慢慢长高’的区别，学小树说‘我慢慢长，不着急’",
                    "age_7_9": "问孩子：‘你觉得一棵小树如果每天用力往上拔，会怎么样？’ 引导孩子理解‘自然成长’比‘假装很高’更重要",
                    "age_10_12": "讨论：‘为什么老子说“企者不立”？’ 让孩子想想生活中哪些事是‘踮脚尖’（急于求成），哪些是‘踏实成长’"
                },
                {
                    "topic": "谁在炫耀？",
                    "age_4_6": "用动物比喻：小孔雀开屏很漂亮，但如果一直转圈炫耀，其他小动物会怎么想？让孩子学小动物说‘我看到了，但我不说’",
                    "age_7_9": "问孩子：‘如果一个人总是说自己多厉害，你心里什么感觉？’ 引导孩子体会‘自夸’让别人不舒服",
                    "age_10_12": "讨论：‘自见者不明’是什么意思？ 让孩子分享一次自己或别人炫耀的经历，并思考‘如果换一种方式会怎样’"
                },
                {
                    "topic": "把智慧带入生活",
                    "age_4_6": "洗澡时和孩子玩‘慢慢洗’游戏：比谁洗得慢但干净，感受‘不着急’的快乐",
                    "age_7_9": "吃饭时问：‘今天有没有谁‘踮脚尖’了？比如作业写得快但字很乱？’ 轻松聊聊，不批评",
                    "age_10_12": "睡前提醒：‘老子说这些不是不让你努力，而是提醒你——真正的成长是慢慢来的，就像你小时候学走路，跌倒了再爬起来，最后稳稳地走。’"
                }
            ],
            "parent_tips": "当孩子急于表现时，轻轻抱抱他说：‘我们像小树一样慢慢长，不着急。’ 你的平静就是最好的榜样。",
            "review_status": "approved",
            "reviewed_by": "何继杰",
            "reviewed_at": "2026-05-13",
            "review_history": [
                {
                    "action": "approved",
                    "by": "何继杰",
                    "at": "2026-05-13T11:32:46Z",
                    "notes": "批量2 Article 11安全检查通过"
                }
            ]
        },
        "25": {
            "chapter": 25,
            "title": "有物混成",
            "core_idea": "很久很久以前，比天和地还要早，有一个安安静静、永远不变、到处运行的东西，它是万物的妈妈。我们叫它“道”。宇宙里有四样最大的：道、天、地、人。人跟着地学，地跟着天学，天跟着道学，道就跟着自己本来的样子走——就像你问“为什么这样”，答案就是“本来就是这样的”。",
            "safety_notes": [
                "避免讨论“先天地生”可能引发的关于宇宙起源的恐惧，比如大爆炸或黑暗虚无，强调温暖和安静。",
                "不要将“道”描述为有意志或会惩罚人的神，以免引发对未知的焦虑。",
                "避免将“人法地”解释为放弃人类努力或消极顺从，而是学习自然的规律。"
            ],
            "interaction_points": [
                {
                    "topic": "万物之母",
                    "age_4_6": "问孩子：“你妈妈是什么样子的？温暖的、抱抱的？那万物的妈妈——道，也像妈妈一样，安安静静地照顾所有东西。”让孩子学一个妈妈抱抱的动作。",
                    "age_7_9": "问孩子：“如果道是万物的妈妈，那它是不是像你的妈妈一样会做饭、会讲故事？道会做什么呢？”引导孩子想象道如何让四季轮回、植物生长。",
                    "age_10_12": "问孩子：“老子说不知道道的名字，勉强叫它‘道’。你觉得如果让你给这个‘万物妈妈’起个名字，你会叫什么？为什么？”鼓励孩子用自己的语言描述。"
                },
                {
                    "topic": "四样最大的",
                    "age_4_6": "伸出四根手指，说：“道、天、地、人，是宇宙里最大的四样东西！你也是其中一样哦！”让孩子也伸出四根手指，一起数。",
                    "age_7_9": "问孩子：“人也是‘四大’之一，你觉得人和道、天、地有什么不一样？人有什么特别的地方？”引导孩子说出人能思考、创造等。",
                    "age_10_12": "问孩子：“老子说‘人亦大’，你觉得人为什么重要？如果人不在‘四大’里，世界会有什么不同？”鼓励思辨。"
                },
                {
                    "topic": "把智慧带入生活",
                    "age_4_6": "洗澡时，看着水流，对孩子说：“水顺着地流，就像人跟着地学。你看水总是往低处流，安安静静的，是不是很像道？”让孩子用手划水。",
                    "age_7_9": "晚饭后，和孩子聊聊：“今天你有没有像地学习的时候？比如看到小草被风吹弯又直起来，你学到了什么？”",
                    "age_10_12": "提醒孩子：“道法自然告诉我们，很多事没有为什么，就是这样的。比如为什么太阳从东边升起？可以慢慢想，不着急。”"
                }
            ],
            "parent_tips": "共读后，不妨带孩子去公园坐一会儿，什么都不说，只是静静感受风吹过、树叶摇动——这就是“道法自然”的样子。",
            "review_status": "approved",
            "reviewed_by": "",
            "reviewed_at": "2026-05-12",
            "review_history": [
                {
                    "action": "created",
                    "by": "extract_meta.py",
                    "at": "2026-05-12T00:00:00Z",
                    "notes": "AI generated - awaiting review"
                },
                {
                    "action": "reviewing",
                    "by": "admin",
                    "at": "2026-05-12T10:39:55.766Z",
                    "notes": ""
                },
                {
                    "action": "approved",
                    "by": "admin",
                    "at": "2026-05-12T10:40:27.514Z",
                    "notes": "何继杰"
                }
            ]
        },
        "26": {
            "chapter": 26,
            "title": "重为轻根",
            "core_idea": "就像大树要有深深的根才能站得稳，我们心里也要有一个安静稳重的“根”，这样不管外面多热闹，我们都能稳稳地做自己，不会轻易被带跑。",
            "safety_notes": [
                "避免将“轻浮”与孩子的活泼好动直接关联，以免让孩子觉得“动”是错的。",
                "避免用“你太浮躁了”等评判性语言，应引导孩子观察自己的状态而非贴标签。",
                "避免将“稳重”与“不犯错”画等号，让孩子知道犯错是成长的一部分。",
                "避免用“失去根基”等比喻引发恐惧，可用“像小树被风吹歪”等温和说法。"
            ],
            "interaction_points": [
                {
                    "topic": "谁更稳当",
                    "age_4_6": "和孩子一起模仿大树和小草：大树（站得稳稳的，不动）和小草（被风吹得摇来摇去）。问孩子：“你猜谁更不容易倒？我们一起学大树站得稳稳的！”",
                    "age_7_9": "问问孩子：“你觉得班里哪些同学做事很稳？比如写字一笔一画，或者排队不推挤。你觉得稳的人有什么好处？”",
                    "age_10_12": "讨论：“为什么说安静比急躁更有力量？你见过哪些‘以静制动’的例子？比如在游戏或比赛中。”"
                },
                {
                    "topic": "安静的力量",
                    "age_4_6": "玩一个“木头人”游戏：大家都不动，看看谁坚持得最久。然后问：“刚才安静的时候，你感觉身体里有没有一种力量？”",
                    "age_7_9": "和孩子一起闭上眼睛，听一分钟周围的声音（鸟叫、空调声等）。然后问：“安静的时候，你是不是听到了更多东西？安静让我们更专注。”",
                    "age_10_12": "聊一聊：“为什么说‘静为躁君’？你遇到过因为急躁而搞砸事情的情况吗？如果当时静下来，会不会不一样？”"
                },
                {
                    "topic": "把智慧带入生活",
                    "age_4_6": "洗澡时，和孩子比赛谁在水里站得更稳（像大树一样）。或者吃饭时，让孩子帮忙端碗，提醒：“手要稳，像大树根一样。”",
                    "age_7_9": "邀请孩子聊聊：“今天有没有什么时刻你觉得自己很稳？或者你看到别人很稳？我们怎么在作业多的时候保持安静？”",
                    "age_10_12": "提醒孩子：“老子的智慧需要慢慢体会。下次你感到急躁时，可以试试先深呼吸三次，看看会发生什么。”"
                }
            ],
            "parent_tips": "当孩子急躁时，不妨先抱抱他，和他一起深呼吸。你的平静，就是孩子最好的“辎重”。",
            "review_status": "approved",
            "reviewed_by": "何继杰",
            "reviewed_at": "2026-05-13",
            "review_history": [
                {
                    "action": "approved",
                    "by": "何继杰",
                    "at": "2026-05-13T11:32:46Z",
                    "notes": "批量2 Article 11安全检查通过"
                }
            ]
        },
        "27": {
            "chapter": 27,
            "title": "善行无辙迹",
            "core_idea": "真正厉害的人做事不留痕迹，就像妈妈为你盖被子时你睡着了不知道一样——最好的帮助是让你感觉不到被帮助。",
            "safety_notes": [
                "避免用‘不留痕迹’暗示孩子可以偷偷做坏事不被发现。",
                "避免比较谁更‘厉害’或‘聪明’，以免引发竞争焦虑。",
                "避免将‘看不见的帮忙’等同于家长替孩子包办一切。"
            ],
            "interaction_points": [
                {
                    "topic": "不留脚印的走路",
                    "age_4_6": "宝宝，你见过小鸟在雪地上走路吗？它的小脚印是不是一踩一个？但如果你轻轻踩着妈妈的脚印走，就不会留下自己的脚印啦！来，我们试试看，你踩着我脚印走，是不是像没走路一样？",
                    "age_7_9": "你玩‘悄悄靠近’游戏时，怎么做到不发出声音？比如想偷偷给妈妈一个惊喜，你会踮起脚尖、慢慢走。老子说真正会走路的人不留脚印，就像你悄悄靠近时，没人发现你来了。你觉得生活中还有哪些事可以做得‘不留痕迹’？",
                    "age_10_12": "老子说‘善行无辙迹’，意思是真正有本事的人做事不张扬。比如你帮同学讲解题目，讲完后让他觉得是自己想出来的，这就是‘不留痕迹’的帮忙。你遇到过这样的高手吗？或者你自己有没有做过类似的‘隐形’好事？"
                },
                {
                    "topic": "看不见的绳结",
                    "age_4_6": "哎呀，鞋带散了！妈妈帮你系个蝴蝶结。你看，绳子一拉就开了。但有一种‘绳结’是用爱做的——比如你和妈妈手拉手，不用绳子也分不开。你试试看，和妈妈拉钩，是不是像打了结一样牢？",
                    "age_7_9": "你和好朋友之间有没有‘秘密约定’？比如一起保守一个小秘密，虽然没拉钩也没写纸条，但你们都记得。老子说真正会打结的人不用绳子，别人也解不开。你觉得是什么让这个约定那么牢固？",
                    "age_10_12": "‘善结无绳约而不可解’——老子用打结比喻人与人之间的信任。比如你和父母之间，即使没有合同，你们也互相信任。这种‘无形的结’是怎么形成的？有没有办法让它更牢固？"
                },
                {
                    "topic": "把智慧带入生活",
                    "age_4_6": "晚上洗澡时，让宝宝帮忙把玩具放回篮子。然后说：‘你帮玩具回家，它们好开心，就像没被搬动过一样！’",
                    "age_7_9": "吃饭时，请孩子观察：妈妈盛饭时有没有‘吧嗒’掉米粒？爸爸夹菜时有没有把汤溅出来？然后一起讨论：怎样做事才能‘不留痕迹’？",
                    "age_10_12": "本章智慧需要慢慢体会。今天可以问问孩子：你觉得今天有没有哪件事你做得‘不留痕迹’？如果暂时没有也没关系，就像种子发芽，需要时间。"
                }
            ],
            "parent_tips": "亲爱的，当你为孩子默默做了很多，而孩子浑然不觉时，别失落——那正是‘善行无辙迹’的智慧在悄悄生长。",
            "review_status": "approved",
            "reviewed_by": "何继杰",
            "reviewed_at": "2026-05-13",
            "review_history": [
                {
                    "action": "approved",
                    "by": "何继杰",
                    "at": "2026-05-13T11:32:46Z",
                    "notes": "批量2 Article 11安全检查通过"
                }
            ]
        },
        "28": {
            "chapter": 28,
            "title": "知其雄守其雌",
            "core_idea": "知道自己的厉害，却选择温柔谦逊，就像小溪往低处流，所有水都汇向它。这样就能回到像婴儿一样纯真快乐的状态。",
            "safety_notes": [
                "避免将‘守雌’解释为软弱或放弃，应强调是主动选择温柔",
                "避免比较孩子之间的强弱，防止引发焦虑",
                "避免使用‘羞辱’一词让孩子感到羞耻，可以用‘低调’替换"
            ],
            "interaction_points": [
                {
                    "topic": "小溪的智慧",
                    "age_4_6": "和孩子一起模仿小溪流水的声音‘哗啦啦’，然后问：小溪为什么能吸引所有小水滴？因为它往低处流，不争不抢。你愿意像小溪一样温柔吗？",
                    "age_7_9": "问问孩子：班上有没有同学很厉害但很谦虚？大家是不是都喜欢和他玩？你觉得为什么厉害的人反而要温柔？",
                    "age_10_12": "讨论：老子说‘知其雄守其雌’，为什么知道强大却选择柔弱？你能举出生活中这样的例子吗？比如一个学霸主动帮助同学，反而更受尊重。"
                },
                {
                    "topic": "像婴儿一样",
                    "age_4_6": "让孩子学婴儿笑和哭的声音，然后问：婴儿是不是很可爱？老子说我们要像婴儿一样纯真，你觉得婴儿有什么特点？",
                    "age_7_9": "聊聊：婴儿什么都不懂，但大家都喜欢。为什么老子说‘复归于婴儿’？是不是说我们要保持好奇和简单？",
                    "age_10_12": "探讨：婴儿状态代表纯真和无限可能。你觉得长大后还能保持‘婴儿心’吗？怎么做？"
                },
                {
                    "topic": "把智慧带入生活",
                    "age_4_6": "洗澡时，让孩子把玩具轻轻放进水里，不溅水花，体验‘温柔’的力量。",
                    "age_7_9": "晚餐时，问问家人：今天有没有谁‘知其雄守其雌’？比如爸爸工作很厉害，但回家很温柔。",
                    "age_10_12": "提醒孩子：本章智慧可以慢慢体会，不急于理解。下次遇到冲突时，试试先温柔回应。"
                }
            ],
            "parent_tips": "今晚睡前，轻轻对孩子说：‘你知道吗？你厉害的时候选择温柔，就像小溪一样，大家都喜欢你。’",
            "review_status": "approved",
            "reviewed_by": "何继杰",
            "reviewed_at": "2026-05-13",
            "review_history": [
                {
                    "action": "approved",
                    "by": "何继杰",
                    "at": "2026-05-13T11:32:46Z",
                    "notes": "批量2 Article 11安全检查通过"
                }
            ]
        },
        "33": {
            "chapter": 33,
            "title": "知人者智",
            "core_idea": "认识自己比认识别人更重要，战胜自己比战胜别人更厉害。知道满足的人最富有，坚持努力的人有志气。真正的长久是活出有意义的人生。",
            "safety_notes": [
                "避免用“战胜自己”引发孩子自我否定，应强调进步而非完美",
                "避免将“知足”解释为不努力，要区分满足与放弃",
                "避免将“死而不亡”直接解释死亡，应侧重精神影响"
            ],
            "interaction_points": [
                {
                    "topic": "认识自己",
                    "age_4_6": "问问孩子：小猫咪照镜子时，它知道镜子里的是自己吗？你能指一指自己的鼻子、耳朵吗？",
                    "age_7_9": "请孩子说说自己最喜欢什么、最害怕什么，然后问：你觉得这些事情让别人知道吗？为什么？",
                    "age_10_12": "引导孩子思考：你觉得自己有哪些优点和缺点？你更了解自己还是更了解好朋友？为什么认识自己很难？"
                },
                {
                    "topic": "战胜自己",
                    "age_4_6": "和孩子玩“忍住笑”游戏：看谁先笑出来。告诉孩子：你忍住了，就是战胜了自己！",
                    "age_7_9": "让孩子分享一个“想放弃但坚持下来”的小故事，比如练字、跳绳，然后问：坚持下来感觉怎么样？",
                    "age_10_12": "讨论：为什么说打败别人容易，打败自己难？你有哪些坏习惯想改掉？我们可以一起想办法。"
                },
                {
                    "topic": "把智慧带入生活",
                    "age_4_6": "吃饭时对孩子说：你今天自己吃光了饭，没有浪费，这就是知足哦！",
                    "age_7_9": "睡前和孩子聊聊：今天有没有什么事情让你觉得自己很棒？哪怕很小的事。",
                    "age_10_12": "提醒孩子：本章的智慧可以慢慢体会，不急于一下子做到，就像种子发芽需要时间。"
                }
            ],
            "parent_tips": "和孩子一起照镜子，做鬼脸，聊聊镜子里外的人。轻松一笑中，孩子就懂了‘自知’。",
            "review_status": "approved",
            "reviewed_by": "",
            "reviewed_at": "2026-05-12",
            "review_history": [
                {
                    "action": "created",
                    "by": "extract_meta.py",
                    "at": "2026-05-12T00:00:00Z",
                    "notes": "AI generated - awaiting review"
                },
                {
                    "action": "reviewing",
                    "by": "admin",
                    "at": "2026-05-12T10:40:32.126Z",
                    "notes": ""
                },
                {
                    "action": "approved",
                    "by": "admin",
                    "at": "2026-05-12T10:41:34.823Z",
                    "notes": "何继杰"
                }
            ]
        },
        "38": {
            "chapter": 38,
            "title": "上德不德",
            "core_idea": "真正的好品德就像小鸟唱歌一样自然，不是故意做给别人看的；而如果我们总想着要讲规则、讲礼貌，那可能已经离真正的善良有点远了。",
            "safety_notes": [
                "避免说'你这样做就不是真善良'，不要评判孩子的行为是否真心。",
                "不要用'虚伪'、'假装'等词评价他人，以免引发孩子对人际关系的焦虑。",
                "当孩子描述淘气、犯错或不听话的行为时，不要将其美化为'返璞归真'或'顺应自然'。可以用平常心回应孩子的情绪，但不将这些行为与《道德经》中的'无为'、'有德'等概念相关联。保持对行为的客观态度，不做道德评判。"
            ],
            "interaction_points": [
                {
                    "topic": "自然的好品德",
                    "age_4_6": "问问孩子：小鸟唱歌是为了让别人夸它吗？还是它自己开心？你什么时候会像小鸟一样，不知不觉就做了好事？",
                    "age_7_9": "和孩子聊聊：你见过有人做了好事就到处说吗？你觉得那样做好事和悄悄做好事有什么不同？你更喜欢哪种？为什么？",
                    "age_10_12": "引导孩子思考：老子说'上德不德'，意思是真正有德的人不觉得自己有德。你觉得做好事不留名和做好事被表扬，哪个更让你感到快乐？为什么？"
                },
                {
                    "topic": "道与德的比喻",
                    "age_4_6": "告诉孩子：太阳是道，阳光是德。太阳发光，阳光照到我们身上。你看到阳光时，会想到太阳吗？",
                    "age_7_9": "和孩子一起观察阳光：太阳看不见但阳光看得见。道就像太阳，德就像阳光。你能想到其他这样的比喻吗？比如：树根和树叶？",
                    "age_10_12": "和孩子讨论：老子说道和德就像太阳和阳光。你觉得生活中哪些东西是'道'（看不见的根本），哪些是'德'（看得见的表现）？比如：爱和拥抱？"
                },
                {
                    "topic": "把智慧带入生活",
                    "age_4_6": "今晚洗澡时，和孩子玩'悄悄帮助'游戏：帮妈妈递毛巾时不说话，看谁做得最自然。",
                    "age_7_9": "邀请孩子回忆：今天有没有哪件好事是你不知不觉就做的？比如帮同学捡笔？和爸爸妈妈分享一下那种感觉。",
                    "age_10_12": "提醒孩子：这一章的智慧很深，不用急着完全明白。以后每次你自然帮助别人时，可以想想老子说的'上德不德'，感受那种自然的力量。"
                }
            ],
            "parent_tips": "亲爱的，和孩子一起读这一章时，不妨也问问自己：我有没有为了显得有德而刻意做什么？放下评判，和孩子一起享受那种自然的善良吧。",
            "review_status": "approved",
            "reviewed_by": "",
            "reviewed_at": "2026-05-12",
            "review_history": [
                {
                    "action": "created",
                    "by": "extract_meta.py",
                    "at": "2026-05-12T00:00:00Z",
                    "notes": "AI generated - awaiting review"
                },
                {
                    "action": "reviewing",
                    "by": "admin",
                    "at": "2026-05-12T10:41:43.717Z",
                    "notes": ""
                },
                {
                    "action": "approved",
                    "by": "admin",
                    "at": "2026-05-12T10:59:33.360Z",
                    "notes": "何继杰"
                }
            ]
        },
        "41": {
            "chapter": 41,
            "title": "上士闻道",
            "core_idea": "真正的好东西，有时候看起来像是反着来的。就像最大的声音反而听不见，最大的形象反而看不见。所以，不要只看表面，用心去感受，会发现不一样的美。",
            "safety_notes": [
                "避免用'笨人'、'聪明人'等标签评价孩子或他人，可改为'不同的人有不同的理解'",
                "避免强调'不被理解'的孤独感，而是说'每个人都需要时间去发现'",
                "避免用'反着来'引发对立思维，强调这是看待事物的不同角度"
            ],
            "interaction_points": [
                {
                    "topic": "看不见的好东西",
                    "age_4_6": "问孩子：'风看不见，但你能感觉到它吗？吹一吹手心，学一学风的声音（呼呼）。还有什么是看不见但存在的？'",
                    "age_7_9": "问孩子：'你觉得最好的朋友有什么特别？是他的外貌还是他对你的好？说说一个别人看不出来但你知道的优点。'",
                    "age_10_12": "讨论：'老子说“大音希声，大象无形”，最伟大的声音反而听不到，最伟大的形象反而看不见。你觉得生活中有什么东西是越深越难用语言描述的？比如爱、勇气？'"
                },
                {
                    "topic": "慢一点也没关系",
                    "age_4_6": "拿出一个玩具或积木，慢慢搭高，对孩子说：'看，慢慢地搭，它才更稳。就像小树慢慢长，才会更高。你试试慢慢走一步？'",
                    "age_7_9": "问孩子：'你做过什么需要耐心等待的事情？比如种一颗种子，或者学一个新本领。等待的时候，你觉得是什么在悄悄发生？'",
                    "age_10_12": "讨论：'大器晚成，意思是真正伟大的东西需要时间慢慢成就。你觉得自己身上有什么能力或品质，需要时间慢慢成长？你愿意等待吗？'"
                },
                {
                    "topic": "把智慧带入生活",
                    "age_4_6": "洗澡时，和孩子玩水：'水软软的，但它能流过任何地方。你看，它绕着小鸭子走，不争不抢，却总能到达想去的地方。'",
                    "age_7_9": "吃饭时，聊聊：'今天有没有什么事情，表面看起来不好，但其实有好处？比如摔了一跤，学会了小心；或者一道菜有点苦，但很健康。'",
                    "age_10_12": "睡前，轻轻说：'这一章的道理很深，不用着急全部明白。就像道一样，慢慢体会，它会在你心里悄悄长大。'"
                }
            ],
            "parent_tips": "和孩子一起，像发现宝藏一样去留意那些“不起眼”的美好。不必急着讲道理，一个拥抱、一个微笑，就是最好的“道”。",
            "review_status": "approved",
            "reviewed_by": "何继杰",
            "reviewed_at": "2026-05-13",
            "review_history": [
                {
                    "action": "approved",
                    "by": "何继杰",
                    "at": "2026-05-13T11:32:46Z",
                    "notes": "批量2 Article 11安全检查通过"
                }
            ]
        },
        "42": {
            "chapter": 42,
            "title": "道生一",
            "core_idea": "世界是从一个简单的东西开始，慢慢变成很多很多的样子。就像一颗小种子长成大树，一个音符变成一首歌。有时候，少一点反而会得到更多。",
            "safety_notes": [
                "避免讨论‘强梁者不得其死’的死亡含义，只强调‘不要逞强’的温和道理",
                "不要用‘孤、寡、不谷’等贬义词形容孩子，避免引发自卑",
                "避免将‘损之而益’解释为‘吃亏是福’，防止孩子误解为被欺负也要忍受"
            ],
            "interaction_points": [
                {
                    "topic": "种子变大树",
                    "age_4_6": "宝贝，你看这颗小种子，它小小的，但能长成高高的大树。你用手比划一下，种子有多小？大树有多大？学学大树摇摇树枝的样子。",
                    "age_7_9": "如果一棵大树一开始就是大树，没有种子阶段，会怎样？你觉得为什么世界要从简单变复杂？",
                    "age_10_12": "老子说‘道生一，一生二，二生三，三生万物’，就像从1开始数数，但世界不是数出来的。你觉得‘一’‘二’‘三’可能代表什么？比如‘一’可以是妈妈，‘二’是爸爸，‘三’是你和我？"
                },
                {
                    "topic": "少一点多一点",
                    "age_4_6": "有时候，你少吃一颗糖，肚子反而更舒服。你试过吗？我们来假装吃糖，然后摸摸肚子，说‘刚刚好’。",
                    "age_7_9": "你玩积木时，是不是有时候搭得太多反而倒了？少用几块反而更稳？生活中有没有‘少反而更好’的例子？",
                    "age_10_12": "原文说‘物或损之而益，或益之而损’，比如减少玩游戏的时间，反而让你学习更专注。你同意吗？能想到一个你自己的例子吗？"
                },
                {
                    "topic": "把智慧带入生活",
                    "age_4_6": "洗澡时，玩水从一杯水倒进大盆里，告诉孩子：‘你看，水从少变多了，就像世界从简单变丰富。’",
                    "age_7_9": "吃饭时，聊聊今天有没有‘少反而好’的事？比如少吃零食后，正餐更香了。",
                    "age_10_12": "本章的智慧慢慢品，就像喝茶。今天先记住‘从简单到复杂’的规律，以后遇到难题时，想想是不是可以从最简单的开始？"
                }
            ],
            "parent_tips": "和孩子一起观察大自然吧，比如看云从一朵变成一片，或者数数一颗豆子长出几片叶子。不用解释太多，让孩子自己发现‘从少变多’的奇妙。",
            "review_status": "approved",
            "reviewed_by": "",
            "reviewed_at": "2026-05-12",
            "review_history": [
                {
                    "action": "created",
                    "by": "extract_meta.py",
                    "at": "2026-05-12T00:00:00Z",
                    "notes": "AI generated - awaiting review"
                },
                {
                    "action": "reviewing",
                    "by": "admin",
                    "at": "2026-05-12T10:59:42.754Z",
                    "notes": ""
                },
                {
                    "action": "approved",
                    "by": "admin",
                    "at": "2026-05-12T11:00:31.790Z",
                    "notes": "何继杰"
                }
            ]
        },
        "44": {
            "chapter": 44,
            "title": "名与身孰亲",
            "core_idea": "我们常常为了追求名声或更多东西而累坏自己，其实健康和平静的心最重要。知道什么时候该停下来，才能快乐长久。",
            "safety_notes": [
                "避免用‘你为了玩具/成绩会生病’等恐吓方式，以免引发焦虑。",
                "不要比较‘别人家孩子’的得失，以免造成压力。",
                "避免将‘知足’解释为‘不要努力’或‘放弃梦想’。"
            ],
            "interaction_points": [
                {
                    "topic": "什么最重要",
                    "age_4_6": "问问孩子：‘小兔子最喜欢胡萝卜，但如果吃太多肚子疼，它还会一直吃吗？’引导孩子用手摸摸肚子说‘疼’。",
                    "age_7_9": "和孩子聊聊：‘你觉得健康和玩具哪个更重要？如果为了攒钱买玩具不睡觉，会怎样？’",
                    "age_10_12": "和孩子讨论：‘名声、财富和健康，你会怎么排序？为什么？’可以引用原文‘名与身孰亲’。"
                },
                {
                    "topic": "什么时候停下来",
                    "age_4_6": "玩‘红灯绿灯’游戏：说到‘停’就静止，体会‘停下来’的感觉。",
                    "age_7_9": "问孩子：‘你玩游戏时，妈妈叫你停下，你是什么感觉？’引导理解‘知止’的好处。",
                    "age_10_12": "讨论：‘有人说知足就是不上进，你觉得呢？老子说的知足是放弃努力吗？’"
                },
                {
                    "topic": "把智慧带入生活",
                    "age_4_6": "洗澡时，水快满了就关掉，告诉宝宝：‘水满了，该停了。’",
                    "age_7_9": "邀请孩子一起观察：家里有没有‘多藏必厚亡’的例子？比如零食买太多吃不完坏掉。",
                    "age_10_12": "提醒孩子：‘这个道理很深，不急着懂，以后慢慢体会。’"
                }
            ],
            "parent_tips": "和孩子一起感受‘够了’的轻松，比如吃完最后一口就开心地放下碗。",
            "review_status": "approved",
            "reviewed_by": "",
            "reviewed_at": "2026-05-12",
            "review_history": [
                {
                    "action": "created",
                    "by": "extract_meta.py",
                    "at": "2026-05-12T00:00:00Z",
                    "notes": "AI generated - awaiting review"
                },
                {
                    "action": "reviewing",
                    "by": "admin",
                    "at": "2026-05-12T11:00:34.973Z",
                    "notes": ""
                },
                {
                    "action": "approved",
                    "by": "admin",
                    "at": "2026-05-12T11:01:27.227Z",
                    "notes": "何继杰"
                }
            ]
        },
        "45": {
            "chapter": 45,
            "title": "大成若缺",
            "core_idea": "就像一棵大树，看起来歪歪扭扭的，却长得最结实。真正厉害的东西，外表可能很普通，甚至有点小缺陷，但用起来却特别棒。",
            "safety_notes": [
                "不要用'你看起来笨'或'你看起来不聪明'来举例，避免伤害孩子自尊。",
                "避免讨论'完美'与'缺陷'的优劣，以免引发孩子对外表的焦虑。",
                "不要用'你觉得自己拙吗'等直接指向孩子的提问。"
            ],
            "interaction_points": [
                {
                    "topic": "缺了一角的积木",
                    "age_4_6": "拿出一块缺了一角的积木，问宝宝：这块积木缺了一角，还能搭高楼吗？试试看！然后一起搭，发现它也能稳稳地立着。",
                    "age_7_9": "问孩子：如果一块积木缺了一角，你觉得它还能用吗？一起试试，然后聊聊：看起来不完美的东西，是不是也能派上用场？你身边有这样的东西吗？",
                    "age_10_12": "引导孩子思考：为什么看起来有缺陷的东西反而好用？比如旧书包破了但还能装书。原文说‘大成若缺’，你觉得生活中哪些东西符合这个道理？"
                },
                {
                    "topic": "谁更会说话",
                    "age_4_6": null,
                    "age_7_9": "问孩子：你觉得话多的人厉害，还是话少的人厉害？然后讲个小故事：小兔子话很少，但每次说话都能帮到朋友，大家都很喜欢它。让孩子学小兔子说一句有帮助的话。",
                    "age_10_12": "讨论：原文说‘大辩若讷’，意思是真正会说话的人看起来嘴笨。你觉得有道理吗？举个例子，比如有人不抢着说话，但一开口就说中要点。你身边有这样的人吗？"
                },
                {
                    "topic": "把智慧带入生活",
                    "age_4_6": "洗澡时，玩水杯：一个杯子装满水，看起来满满的，但还能再放几颗小石子吗？试试看，发现水会溢出来，但空杯子却能装更多。告诉宝宝：有时候空空的反而能装更多哦。",
                    "age_7_9": "邀请孩子聊聊：家里有没有什么东西看起来旧旧的、有瑕疵，但用起来特别好？比如妈妈的老水壶、爸爸的旧工具。一起找找，感受‘大成若缺’的生活智慧。",
                    "age_10_12": "提醒孩子：这一章的智慧很深，不用急着完全懂。以后遇到‘看起来不完美’的东西或人，可以多想想它是不是‘用起来很好’。慢慢体会，生活会更有趣。"
                }
            ],
            "parent_tips": "和孩子一起发现生活中那些‘不完美却好用’的小物件，就像发现宝藏一样，会很有趣哦。",
            "review_status": "approved",
            "reviewed_by": "何继杰",
            "reviewed_at": "2026-05-13",
            "review_history": [
                {
                    "action": "approved",
                    "by": "何继杰",
                    "at": "2026-05-13T11:32:46Z",
                    "notes": "批量2 Article 11安全检查通过"
                }
            ]
        },
        "46": {
            "chapter": 46,
            "title": "天下有道",
            "core_idea": "心里知道什么时候说‘够了’，就会一直感到满足。就像喝水喝到刚刚好最舒服，再多就撑着了。",
            "safety_notes": [
                "避免用‘战争’‘打仗’等词引发恐惧，可用‘马儿在和平时候拉车，在乱跑时候被拉走’替代。",
                "不要将‘不知足’等同于‘不能有梦想’，要区分‘贪心’和‘努力’。",
                "避免说‘不知足是错的’，改用‘有时候想要太多会让自己不开心’。"
            ],
            "interaction_points": [
                {
                    "topic": "小马的故事",
                    "age_4_6": "带孩子看马或小马的图片，问：‘马儿什么时候开心？是拉车耕地的时候，还是被拉去乱跑的时候？’让孩子学马叫或指一指马。",
                    "age_7_9": "问：‘如果马儿总是想要更多草料，它会怎么样？’引导孩子联系自己：有没有想要更多玩具的时候？后来开心吗？",
                    "age_10_12": "讨论：‘为什么老子说最大的灾祸是不知足？’可以结合历史故事或身边事例，比如有人因为贪心做错事。"
                },
                {
                    "topic": "知道‘够了’",
                    "age_4_6": "吃零食时问：‘你觉得吃几块饼干就刚刚好？’让孩子用手比划‘够了’的手势。",
                    "age_7_9": "玩游戏时问：‘什么时候你会觉得“够了”，不想再玩了？’让孩子说说自己的感受。",
                    "age_10_12": "讨论：‘知足会不会让人不努力？’引导区分‘满足’和‘停止成长’，举例如‘我满足于现在的成绩，但我还可以更好’。"
                },
                {
                    "topic": "把智慧带入生活",
                    "age_4_6": "洗澡时玩水，问：‘水倒多少刚好？’让孩子感受‘刚刚好’的快乐。",
                    "age_7_9": "邀请孩子分享：‘今天有没有哪件事让你觉得“够了，很满足”？’",
                    "age_10_12": "提醒孩子：‘知足不是不进步，而是珍惜已经拥有的。’可以慢慢体会。"
                }
            ],
            "parent_tips": "和孩子一起，发现生活中‘刚刚好’的小瞬间，比如一碗饭、一个拥抱。不必刻意说教，你满足的样子就是最好的示范。",
            "review_status": "approved",
            "reviewed_by": "何继杰",
            "reviewed_at": "2026-05-13",
            "review_history": [
                {
                    "action": "approved",
                    "by": "何继杰",
                    "at": "2026-05-13T11:32:46Z",
                    "notes": "批量2 Article 11安全检查通过"
                }
            ]
        },
        "48": {
            "chapter": 48,
            "title": "为学日益",
            "core_idea": "学习就像往口袋里装东西，越来越多；但有时候，我们需要把不必要的东西拿出来，口袋才能轻松打开，做事也更顺手。",
            "safety_notes": [
                "不要让孩子觉得学习知识是不好的，避免说“学太多会变笨”之类的话。",
                "不要将“无为”解释成“什么都不做”，避免孩子误解为偷懒。",
                "避免用“折腾”这个词批评孩子的活跃行为，以免引发焦虑。"
            ],
            "interaction_points": [
                {
                    "topic": "收拾玩具",
                    "age_4_6": "拿出孩子的一筐玩具，问：“玩具太多了，我们找小汽车是不是很慢？如果只留下几个最喜欢的，是不是一下子就找到了？”让孩子亲手挑出几个玩具，体验“少反而快”。",
                    "age_7_9": "和孩子一起整理书桌，问：“你觉得东西少的时候，写作业是不是更专心？为什么？”鼓励孩子说出自己的感受。",
                    "age_10_12": "讨论：有时候我们学了很多技能，但真正需要的时候反而不知道用哪个。你觉得是学得越多越好，还是学精几样更重要？"
                },
                {
                    "topic": "小树苗长大",
                    "age_4_6": "带孩子看一棵小树，问：“小树需要很多花哨的东西吗？它只需要阳光、水和泥土就够了。”让孩子学小树“吸收”阳光的动作。",
                    "age_7_9": "问孩子：“如果小树每天被施肥、浇水、修剪，它会不会反而长不好？为什么？”引导孩子理解“过多照顾”可能适得其反。",
                    "age_10_12": "和孩子聊聊：大自然中，哪些事情是“无为”的？比如太阳升起、花朵开放，它们没有刻意去做，却自然发生。"
                },
                {
                    "topic": "把智慧带入生活",
                    "age_4_6": "洗澡时，和孩子玩“水杯倒水”游戏：倒满水，再慢慢倒掉，说：“有时候倒掉一些，杯子才能装新东西。”",
                    "age_7_9": "晚饭后，邀请孩子分享今天有没有“做了很多但感觉乱糟糟”的事情？一起想想怎么简化。",
                    "age_10_12": "提醒孩子：本章的道理就像整理房间，不用一次做到完美，慢慢来，每天少一点点不必要的杂念。"
                }
            ],
            "parent_tips": "共读时，不妨先放下“教”的念头，和孩子一起像发现新大陆一样聊聊“少”的好处。",
            "review_status": "approved",
            "reviewed_by": "",
            "reviewed_at": "2026-05-12",
            "review_history": [
                {
                    "action": "created",
                    "by": "extract_meta.py",
                    "at": "2026-05-12T00:00:00Z",
                    "notes": "AI generated - awaiting review"
                },
                {
                    "action": "reviewing",
                    "by": "admin",
                    "at": "2026-05-12T11:01:32.982Z",
                    "notes": ""
                },
                {
                    "action": "approved",
                    "by": "admin",
                    "at": "2026-05-12T11:02:36.330Z",
                    "notes": "何继杰"
                }
            ]
        },
        "51": {
            "chapter": 51,
            "title": "道生之德畜之",
            "core_idea": "就像爸爸妈妈把你带到这个世界，用爱照顾你长大，但从不觉得你是他们的东西，也不要求你回报——大自然的道和德也是这样，默默创造一切，让万物自由生长，这就是最伟大的爱。",
            "safety_notes": [
                "避免用‘道’或‘德’来评判孩子的行为好坏，比如‘你这样做就不尊重道了’。",
                "不要用‘万物自然生长’来否定父母或老师的照顾和引导责任。",
                "避免将‘不占有’理解为父母不关心孩子，要强调爱是无私的，但依然有保护。"
            ],
            "interaction_points": [
                {
                    "topic": "种子和妈妈",
                    "age_4_6": "拿出一颗种子，让孩子摸一摸，说：‘种子宝宝在泥土里，太阳和雨水照顾它长大，就像妈妈照顾你一样。’然后让孩子学小种子发芽的样子，慢慢站起来。",
                    "age_7_9": "问孩子：‘如果你是一颗种子，谁像阳光和雨露一样帮助你长大？除了爸爸妈妈，还有谁？’鼓励孩子说出老师、朋友等。",
                    "age_10_12": "讨论：‘道生万物却不占有，就像太阳照耀大地却不要求回报。你觉得这种‘不占有’的爱，在我们的生活中有哪些例子？’"
                },
                {
                    "topic": "谁的功劳",
                    "age_4_6": null,
                    "age_7_9": "和孩子一起搭积木，完成后问：‘如果积木倒了，是谁的错？如果搭得很高，是谁的功劳？’引导孩子理解事情成功有很多因素。",
                    "age_10_12": "讨论：‘老子说‘生而不有，为而不恃’，意思是创造了却不居功。你见过这样谦虚的人吗？你觉得为什么他们不居功？’"
                },
                {
                    "topic": "把智慧带入生活",
                    "age_4_6": "洗澡时，让孩子看水中的泡泡，说：‘泡泡来了又走了，就像大自然创造了很多东西，但不一直抓着它们。’",
                    "age_7_9": "吃饭时，问问孩子：‘这顿饭是谁做的？还有谁帮助了它来到餐桌？’让孩子体会很多人的默默付出。",
                    "age_10_12": "提醒孩子：‘今天聊的‘玄德’很深奥，如果你现在不完全懂也没关系，可以在生活中慢慢观察和体会。’"
                }
            ],
            "parent_tips": "和孩子一起散步时，指着一棵树说：‘你看，它就这样静静地长着，不需要谁表扬。’然后轻轻抱抱孩子，什么都不用说。",
            "review_status": "approved",
            "reviewed_by": "何继杰",
            "reviewed_at": "2026-05-13",
            "review_history": [
                {
                    "action": "approved",
                    "by": "何继杰",
                    "at": "2026-05-13T11:32:46Z",
                    "notes": "批量2 Article 11安全检查通过"
                }
            ]
        },
        "52": {
            "chapter": 52,
            "title": "天下有始",
            "core_idea": "所有事物都有一个像妈妈一样的源头，知道了这个源头，就能理解身边的一切；理解了身边的一切，再回到这个源头，心里就踏实了。",
            "safety_notes": [
                "避免用'没身不殆'、'终身不救'等词汇吓到孩子，可替换为'安全'、'轻松'等正面表述。",
                "讨论'塞其兑，闭其门'时，避免让孩子误解为'要一直捂着耳朵闭着眼睛'，而是强调'需要专注时可以关掉干扰'。",
                "不要将'开其兑，济其事'与孩子的正常探索和学习挂钩，避免让孩子觉得探索世界是错的。"
            ],
            "interaction_points": [
                {
                    "topic": "找找妈妈",
                    "age_4_6": "问孩子：'你的妈妈在哪里？'让孩子指一指妈妈。然后说：'就像你有妈妈一样，大树也有妈妈，它的妈妈是种子；小鸟的妈妈是鸟妈妈，它们都知道自己的家在哪里。'",
                    "age_7_9": "问孩子：'你知道你最爱吃的苹果是从哪里来的吗？'引导孩子说出苹果树、种子。然后问：'那你知道种子又是从哪里来的吗？'一起讨论万物的源头。",
                    "age_10_12": "问孩子：'你觉得'妈妈'在这里只是指妈妈吗？还是可以比喻什么？'引导孩子思考'源头'的概念，比如：'我们学的知识也有源头吗？'"
                },
                {
                    "topic": "关掉小喇叭",
                    "age_4_6": "和孩子玩'安静游戏'：假装关掉耳朵的小喇叭，嘴巴的小喇叭，然后听听周围有什么小小的声音？比如钟表的滴答声。",
                    "age_7_9": "问孩子：'什么时候你需要把耳朵'关掉'？比如写作业时，电视声音太大怎么办？'一起想个办法，比如戴上耳机或者关上门。",
                    "age_10_12": "问孩子：'你觉得为什么老子说'塞其兑，闭其门'会'终身不勤'？'讨论一下：是不是有时候信息太多反而让人累？怎么找到自己的安静时间？"
                },
                {
                    "topic": "把智慧带入生活",
                    "age_4_6": "今天洗澡时，和孩子一起观察水里的泡泡：'泡泡从哪里来？又到哪里去？'体会万物的开始和结束。",
                    "age_7_9": "晚饭时，和孩子聊聊：'我们吃的米饭是从哪里来的？'从稻田到餐桌，感受万物的联系。",
                    "age_10_12": "提醒孩子：'这一章的道理可以慢慢想，比如遇到难题时，回到问题的根本，也许就有答案了。'"
                }
            ],
            "parent_tips": "陪孩子读这一章时，不妨也想想自己的'根'在哪里。那些让你感到踏实和安心的事，就是你的'母'。",
            "review_status": "approved",
            "reviewed_by": "何继杰",
            "reviewed_at": "2026-05-13",
            "review_history": [
                {
                    "action": "approved",
                    "by": "何继杰",
                    "at": "2026-05-13T11:32:46Z",
                    "notes": "批量2 Article 11安全检查通过"
                }
            ]
        },
        "54": {
            "chapter": 54,
            "title": "善建者不拔",
            "core_idea": "就像盖房子要先打好地基一样，我们想让自己和世界变得更好，得先从小事做起，从自己做起。把自己修好了，就像一颗小石子扔进水里，波纹会一圈圈地往外扩散，慢慢影响到家人、朋友，甚至更远的地方。",
            "safety_notes": [
                "避免将‘修德’解释为必须完美无缺，以免孩子感到压力。",
                "避免用‘子孙祭祀不辍’引发对死亡或祖先的恐惧。",
                "避免强调‘修身’是唯一途径，以免孩子感到孤立或否定其他努力。"
            ],
            "interaction_points": [
                {
                    "topic": "小石子，大波纹",
                    "age_4_6": "和宝宝一起玩水：在水盆里扔一颗小石子，看波纹一圈圈变大。告诉宝宝：你帮妈妈拿拖鞋，就像这颗小石子，家里就多了一圈开心的波纹！",
                    "age_7_9": "问问孩子：‘你做过什么小事，像小石子一样让周围变好了？比如帮了同学、整理了房间？’ 一起画一张‘波纹图’，把小事画在中心，往外画影响。",
                    "age_10_12": "和孩子探讨：‘为什么老子说修身要从自己开始？如果一个人自己都管不好，却想改变世界，会怎样？’ 引导孩子思考‘根基’的重要性。"
                },
                {
                    "topic": "盖房子的地基",
                    "age_4_6": "用积木搭一个房子，先搭大底座。问宝宝：‘如果底座很小，房子会怎样？’ 一起轻轻推倒小底座房子，再搭大底座房子，看哪个更稳。",
                    "age_7_9": "请孩子观察一棵大树：根扎得深，风吹不倒。问：‘你觉得自己哪些习惯像树根一样，能让你变得更稳？’ 比如每天练字、按时睡觉。",
                    "age_10_12": "和孩子聊聊：‘老子说修之于身、家、乡、邦、天下，你觉得这个顺序可以颠倒吗？比如先管天下，再管自己？’ 鼓励孩子用例子说明。"
                },
                {
                    "topic": "把智慧带入生活",
                    "age_4_6": "洗澡时，和孩子玩‘小石子游戏’：每做一件好事，就用手在水里画一个圈，看谁画的圈多。",
                    "age_7_9": "晚饭时，全家分享今天自己做的‘小石子’好事，比如帮邻居按电梯、给植物浇水，然后一起画波纹。",
                    "age_10_12": "提醒孩子：‘老子的智慧就像种子，种下去慢慢长。今天聊的‘修身’可以慢慢想，不用马上做到。爸爸妈妈也在学呢！’"
                }
            ],
            "parent_tips": "亲爱的家长，和孩子一起做‘小石子’吧——从你做起，一个微笑、一句鼓励，波纹会慢慢荡开。不用急，地基要慢慢打。",
            "review_status": "approved",
            "reviewed_by": "何继杰",
            "reviewed_at": "2026-05-13",
            "review_history": [
                {
                    "action": "approved",
                    "by": "何继杰",
                    "at": "2026-05-13T11:32:46Z",
                    "notes": "批量2 Article 11安全检查通过"
                }
            ]
        },
        "55": {
            "chapter": 55,
            "title": "含德之厚",
            "core_idea": "像小婴儿一样，虽然软软的，但小手握得紧紧，哭一天嗓子也不哑——这就是最棒的生命力！我们不用逞强，自然放松，反而更有力量。",
            "safety_notes": [
                "避免用‘毒虫、猛兽、凶鸟’等吓唬孩子，可以说成‘小虫子、大动物、小鸟’并强调它们不会伤害小婴儿。",
                "不要将‘未知牝牡之合’解释为性器官或性行为，只需说‘小婴儿什么都不懂，但身体很健康’。",
                "避免将‘不道早已’说成‘会死掉’，改为‘会不舒服、容易累’等温和表达。"
            ],
            "interaction_points": [
                {
                    "topic": "小拳头握紧",
                    "age_4_6": "宝宝，来握握你的小拳头，是不是很紧呀？像小婴儿一样，软软的却很有力气！我们来学小婴儿握拳头，再学小猫伸爪子，哪个更用力？",
                    "age_7_9": "你试过紧紧握住一个东西很久吗？比如握紧一支笔，手会累吗？小婴儿能一直握紧拳头却不累，你觉得为什么？",
                    "age_10_12": "老子说婴儿‘骨弱筋柔而握固’，看似柔弱却握得很稳。你生活中有没有‘柔弱胜刚强’的例子？比如水很软却能穿石。"
                },
                {
                    "topic": "哭不哑的秘密",
                    "age_4_6": "小婴儿哭很久嗓子也不哑，我们学学小婴儿‘啊——’地叫，看看能叫多久？再学小猫咪‘喵——’，哪个更轻松？",
                    "age_7_9": "你哭过很久吗？嗓子会哑吗？为什么小婴儿哭一整天都不哑？可能他们哭得很自然，不使劲喊。我们来试试自然呼吸和使劲喊的区别。",
                    "age_10_12": "‘终日号而不嗄，和之至也’，老子说因为‘和’。你觉得‘和’是什么意思？是心里平静还是身体放松？你什么时候感觉最‘和’？"
                },
                {
                    "topic": "把智慧带入生活",
                    "age_4_6": "洗澡时，让身体像小婴儿一样软软的浮在水里，不使劲，感受水的拥抱。",
                    "age_7_9": "今天遇到困难时，先像小婴儿一样深呼吸，不急着用力，看看会不会更顺利？和爸妈分享你的发现。",
                    "age_10_12": "本章的智慧可以慢慢品，不用马上做到。下次觉得自己在‘逞强’时，想想婴儿的状态，也许会有新感悟。"
                }
            ],
            "parent_tips": "共读时，可以轻轻握住孩子的手，感受那份柔软和力量。不用解释太多，一起模仿婴儿的呼吸和笑声，就是最好的体验。",
            "review_status": "approved",
            "reviewed_by": "",
            "reviewed_at": "2026-05-12",
            "review_history": [
                {
                    "action": "created",
                    "by": "extract_meta.py",
                    "at": "2026-05-12T00:00:00Z",
                    "notes": "AI generated - awaiting review"
                },
                {
                    "action": "reviewing",
                    "by": "admin",
                    "at": "2026-05-12T11:02:39.606Z",
                    "notes": ""
                },
                {
                    "action": "approved",
                    "by": "admin",
                    "at": "2026-05-12T11:03:27.522Z",
                    "notes": "何继杰"
                }
            ]
        },
        "62": {
            "chapter": 62,
            "title": "道者万物之奥",
            "core_idea": "道就像太阳，不管你是好人还是犯了错，它都温暖地照耀着你，给你机会变得更好。世界上最珍贵的不是金银珠宝，而是这种包容和成长的力量。",
            "safety_notes": [
                "避免用'坏人'、'罪犯'等标签化语言，可以说'有时做错事的人'或'不小心犯错的人'",
                "不要强调'有罪以免'可能让孩子误解为犯错不用承担后果，应引导为'道给我们改正的机会'",
                "避免将'道'描述成有求必应的神仙，而是自然规律般的包容与支持",
                "不要用'抛弃'、'丢弃'等词引发分离焦虑，用'不放弃'、'始终陪伴'替代"
            ],
            "interaction_points": [
                {
                    "topic": "太阳不挑人",
                    "age_4_6": "宝宝，看窗外的太阳，它是不是照着大树、小花，也照着小蚂蚁？太阳不会说'我只照好孩子'，它照所有人。道也像太阳一样，对每个人都好。你学小太阳笑一个吧！",
                    "age_7_9": "你觉得太阳有没有偏心？为什么它既照好人也照坏人？如果有一天你犯错了，你觉得太阳还会照你吗？那爸爸妈妈和老师呢？",
                    "age_10_12": "老子说'道'像庇护所，好人坏人都在其中。你怎么理解这种'不抛弃'？如果一个人做了坏事，道还保护他，这是不是不公平？我们聊聊公平和包容的区别。"
                },
                {
                    "topic": "宝贝大比拼",
                    "age_4_6": "拿出你的玩具，我们来比一比哪个最珍贵？小汽车、布娃娃……但你知道吗？有一个东西比所有玩具都珍贵，那就是'道'——它让我们学会分享、学会原谅。你愿意把它放在心里吗？",
                    "age_7_9": "如果你有世界上最大的钻石和一箱金子，但没有人爱你、没有人原谅你的错误，你会开心吗？老子说'道'比这些宝物都重要，你觉得为什么？",
                    "age_10_12": "老子说当上皇帝、拥有拱璧驷马都不如'坐进此道'。你觉得'道'带来的满足和物质财富带来的满足有什么不同？你更想要哪一种？"
                },
                {
                    "topic": "把智慧带入生活",
                    "age_4_6": "今天洗澡时，水暖暖的，就像道一样拥抱你。你可以对水说：谢谢水，谢谢道！",
                    "age_7_9": "今天和家人一起吃饭时，聊聊：有没有谁做错了事，但我们还是一家人，互相不放弃？像道一样包容。",
                    "age_10_12": "今天可以慢慢思考：道给了我们改正的机会。你最近有没有需要给自己或别人一个机会的事？不着急，可以过几天再和爸妈聊。"
                }
            ],
            "parent_tips": "亲爱的家长，和孩子一起感受道的包容：犯错时不说'你怎么又这样'，而是'没关系，我们重新试试'。你的拥抱就是孩子心中的太阳。",
            "review_status": "approved",
            "reviewed_by": "何继杰",
            "reviewed_at": "2026-05-13",
            "review_history": [
                {
                    "action": "approved",
                    "by": "何继杰",
                    "at": "2026-05-13T11:32:46Z",
                    "notes": "批量2 Article 11安全检查通过"
                }
            ]
        },
        "63": {
            "chapter": 63,
            "title": "为无为",
            "core_idea": "就像搭积木，从最小的一块开始，慢慢就能搭成大大的城堡。做事情不用着急，从小事做起，认真对待，最后什么难事都难不倒你。",
            "safety_notes": [
                "避免说'你不从小事做起就成不了大事'，这会造成压力，要换成'我们看看怎么从小事开始吧'。",
                "避免用'报怨以德'要求孩子原谅别人，要引导孩子先表达感受再选择如何回应。",
                "避免说'你总是把事想得太简单'，这容易让孩子害怕尝试，要换成'这件事好像有点挑战，我们一起看看哪里容易开始'。"
            ],
            "interaction_points": [
                {
                    "topic": "小蚂蚁搬食物",
                    "age_4_6": "宝贝，你看地上有小蚂蚁在搬一块大饼干吗？蚂蚁是一下子搬起来的，还是先搬一小块，再搬一小块？我们来学蚂蚁搬东西，用手指捏一点橡皮泥，再捏一点，最后变成一个大球！",
                    "age_7_9": "如果蚂蚁想一次搬走整个饼干，会发生什么？那我们做一件事的时候，比如收拾玩具，是一下子收拾完容易，还是先收拾一个区域再收拾另一个容易？你来当小蚂蚁，试试看怎么从最乱的那个角落开始。",
                    "age_10_12": "老子说'天下难事必作于易'，就像蚂蚁搬食物，再难的任务也可以分解成简单的小步骤。你最近有没有遇到什么觉得很难的事情？我们可以一起把它拆成小步骤，从最容易的一步开始。"
                },
                {
                    "topic": "搭积木城堡",
                    "age_4_6": "我们来搭一个高高的城堡！先放一块积木，再放一块，慢慢搭高。如果一下子放很多块会怎么样？对，会倒掉。我们一块一块来，就像老子爷爷说的'为大于其细'。",
                    "age_7_9": "你想搭一个什么样的城堡？如果一开始就想搭一座有塔楼和城墙的大城堡，可能会觉得很难。但如果先搭一个简单的塔，再慢慢加墙，是不是就简单多了？你最近有没有什么'大城堡'想搭？我们可以从哪块'小积木'开始？",
                    "age_10_12": "老子说'圣人终不为大，故能成其大'，意思是真正厉害的人不急着做大事，而是把每件小事做好，最后自然成就了大事。你同意吗？能举个例子吗？比如学一门乐器，是一开始就练很难的曲子，还是先练音阶？"
                },
                {
                    "topic": "把智慧带入生活",
                    "age_4_6": "宝宝，今天刷牙的时候，我们像小蚂蚁一样，先刷上面一排牙，再刷下面一排牙，一颗一颗刷干净！你数数看刷了几颗牙？",
                    "age_7_9": "今天晚饭后，我们来玩一个'小事清单'游戏：每人说一件今天做的小事（比如自己系鞋带），然后看看这些小事加起来，今天是不是做了很多大事？",
                    "age_10_12": "今天可以想一想：有没有什么事你一开始觉得很难，但后来发现从简单处入手就解决了？或者有没有什么事你随口答应别人，但后来发现做不到？老子说'轻诺必寡信'，提醒我们答应前要想想。"
                }
            ],
            "parent_tips": "和孩子一起读的时候，不妨用积木或乐高做个游戏：搭一个作品，然后拆成小块，再一起重建。你会发现，孩子自己就懂了。",
            "review_status": "approved",
            "reviewed_by": "",
            "reviewed_at": "2026-05-12",
            "review_history": [
                {
                    "action": "created",
                    "by": "extract_meta.py",
                    "at": "2026-05-12T00:00:00Z",
                    "notes": "AI generated - awaiting review"
                },
                {
                    "action": "reviewing",
                    "by": "admin",
                    "at": "2026-05-12T11:04:04.221Z",
                    "notes": ""
                },
                {
                    "action": "approved",
                    "by": "admin",
                    "at": "2026-05-12T11:05:01.730Z",
                    "notes": "何继杰"
                }
            ]
        },
        "64": {
            "chapter": 64,
            "title": "慎终如始",
            "core_idea": "就像小树苗慢慢长成大树一样，所有大事都是从很小很小的事情开始的。从头到尾都认真对待，就像对待第一步那样认真，这样就能做好每一件事。",
            "safety_notes": [
                "避免用失败、犯错等词批评孩子，如'你这样肯定会失败'",
                "避免用'你总是半途而废'等标签化语言",
                "避免将'无为'解释为什么都不做，应强调自然、不强迫",
                "避免比较孩子之间的做事速度或成果"
            ],
            "interaction_points": [
                {
                    "topic": "大树从哪里来",
                    "age_4_6": "和孩子一起看一棵大树，问：这棵树小时候是什么样的？用手比划一下种子有多大。然后假装自己是小种子，慢慢长大成大树，学大树摇摇树枝。",
                    "age_7_9": "找一张种子长成大树的过程图，问：你觉得大树长成需要什么？如果每天只长一点点，最后会怎样？你做过什么事也是一点点积累起来的？",
                    "age_10_12": "讨论：为什么说'合抱之木，生于毫末'？你同意做小事才能成大事吗？能不能举一个你身边的例子？比如学乐器、练字。"
                },
                {
                    "topic": "坚持到最后",
                    "age_4_6": "和孩子玩搭积木，搭到一半时故意说：哎呀好累，不想搭了。然后问孩子：如果现在不搭了，会怎样？我们像小蚂蚁一样，一步一步搭完好不好？",
                    "age_7_9": "问孩子：你最近有没有什么事快做完了却想放弃？比如拼图、作业。老子说'慎终如始'，意思是结尾和开头一样认真。你觉得这样会有什么好处？",
                    "age_10_12": "讨论：为什么很多人'常于几成而败之'？你觉得怎样才能避免这种情况？你自己有没有类似的经历？下次可以怎么做？"
                },
                {
                    "topic": "把智慧带入生活",
                    "age_4_6": "洗澡时，和孩子一起把浴缸里的玩具一点点收好，说：我们像小蚂蚁一样，一个一个收，收完就干净啦！每收一个就夸一句。",
                    "age_7_9": "晚饭时，聊聊家里有没有什么需要坚持做的小事，比如每天浇花、整理书包。让孩子说说坚持做这件事的感受。",
                    "age_10_12": "提醒孩子：这个智慧可以慢慢体会，不用一次就做到。就像种子发芽需要时间，我们也可以慢慢练习'慎终如始'。"
                }
            ],
            "parent_tips": "和孩子一起种一颗小种子，每天观察它的变化。不用刻意说教，让自然的力量悄悄告诉孩子：每一步都算数。",
            "review_status": "approved",
            "reviewed_by": "何继杰",
            "reviewed_at": "2026-05-13",
            "review_history": [
                {
                    "action": "approved",
                    "by": "何继杰",
                    "at": "2026-05-13T11:32:46Z",
                    "notes": "批量2 Article 11安全检查通过"
                }
            ]
        },
        "67": {
            "chapter": 67,
            "title": "三宝",
            "core_idea": "老子爷爷有三件宝贝：爱别人、不浪费、不抢着当第一。爱别人让我们变得勇敢，不浪费让我们拥有更多，不抢着当第一反而能成为大家喜欢的领头人。",
            "safety_notes": [
                "避免讨论战争场景，如'以战则胜'可能引发恐惧，改为强调慈爱带来的保护和团结。",
                "避免将'不敢为天下先'误解为消极退缩，应解释为不争抢但可以主动帮助他人。",
                "避免用'死矣'等字眼引发焦虑，可转化为'如果丢掉宝贝，事情就会变得糟糕'。"
            ],
            "interaction_points": [
                {
                    "topic": "慈爱小勇士",
                    "age_4_6": "宝宝，妈妈爱你所以会保护你。你爱小猫咪，所以会轻轻摸它。爱让我们变得勇敢！你爱谁？你会怎么保护他？",
                    "age_7_9": "你什么时候因为爱别人而变得勇敢？比如保护弟弟妹妹、帮朋友解围？说说看，爱给了你什么力量？",
                    "age_10_12": "老子说'慈故能勇'，爱是勇气的来源。你同意吗？有没有例子说明没有爱的勇敢可能是鲁莽？"
                },
                {
                    "topic": "节俭小能手",
                    "age_4_6": "宝宝，我们玩水的时候把水龙头开小一点，这样水就不会浪费。你还能想到怎么不浪费？比如吃饭不剩饭？",
                    "age_7_9": "你有哪些'节俭'的好习惯？比如用零花钱买需要的东西而不是乱花。节俭之后，你得到了什么？",
                    "age_10_12": "老子说'俭故能广'，不浪费反而能拥有更多。你觉得在时间和精力上怎么做到'俭'？比如少玩手机多学习？"
                },
                {
                    "topic": "把智慧带入生活",
                    "age_4_6": "宝宝，今天吃饭时我们比一比谁不浪费一粒米，谁就是节俭小明星！",
                    "age_7_9": "今晚和爸爸妈妈聊聊：家里有没有'不抢先'的例子？比如排队时耐心等待，结果反而更开心？",
                    "age_10_12": "这章的道理很深，你可以慢慢想。下次遇到想争第一的时候，试试'不抢先'，看看会发生什么。"
                }
            ],
            "parent_tips": "和孩子一起找找生活中的'三宝'：一个拥抱（慈）、一次节约（俭）、一次谦让（不争先）。你也会发现自己的'三宝'哦。",
            "review_status": "approved",
            "reviewed_by": "",
            "reviewed_at": "2026-05-12",
            "review_history": [
                {
                    "action": "created",
                    "by": "extract_meta.py",
                    "at": "2026-05-12T00:00:00Z",
                    "notes": "AI generated - awaiting review"
                },
                {
                    "action": "reviewing",
                    "by": "admin",
                    "at": "2026-05-12T11:05:05.994Z",
                    "notes": ""
                },
                {
                    "action": "approved",
                    "by": "admin",
                    "at": "2026-05-12T11:08:00.182Z",
                    "notes": "何继杰"
                }
            ]
        },
        "71": {
            "chapter": 71,
            "title": "知不知",
            "core_idea": "聪明的孩子知道自己还有不知道的东西，就像小兔子知道森林里还有没去过的地方一样。承认“我不知道”不是笨，是勇敢的开始。",
            "safety_notes": [
                "避免说“不知道就是笨”或“装懂就是坏”，不要让孩子因承认不知道而感到羞耻。",
                "不要用“你有病”来批评孩子，老子说的“病”是比喻，不是真的生病。",
                "避免将“不知道”等同于“放弃思考”，要强调这是探索的第一步。"
            ],
            "interaction_points": [
                {
                    "topic": "小松鼠的坚果",
                    "age_4_6": "问孩子：小松鼠找到一颗坚果，它会不会说‘我知道所有坚果在哪’？让孩子学小松鼠摇头说‘我不知道，我还要找更多’。",
                    "age_7_9": "问孩子：你觉得自己像不像小松鼠？有时候我们知道一些事情，但还有很多不知道的。能不能举个例子，比如你知道怎么拼自己的名字，但不知道怎么写某个新字？",
                    "age_10_12": "问孩子：老子说‘知不知’是高明，你同意吗？有没有哪次你承认不知道，结果学到了新东西？和‘装懂’比起来，哪种更让你进步？"
                },
                {
                    "topic": "猫头鹰的智慧",
                    "age_4_6": "让孩子学猫头鹰转动头：猫头鹰知道晚上有好多声音它听不清楚，但它不会假装知道。问问孩子：你什么时候会像猫头鹰一样说‘我不确定’？",
                    "age_7_9": "和孩子讨论：猫头鹰为什么是智慧的象征？因为它先观察再行动。我们也可以这样：遇到不懂的问题，先说‘让我想想’，而不是马上回答。",
                    "age_10_12": "引导孩子思考：如果圣人不犯‘以为自己知道’的毛病，那他们怎么学习？是不是因为他们总是保持好奇？你愿意做这样的人吗？"
                },
                {
                    "topic": "把智慧带入生活",
                    "age_4_6": "洗澡时玩‘我知道/不知道’游戏：妈妈问‘泡泡是怎么来的？’孩子可以说‘我不知道，但我想知道！’然后一起找答案。",
                    "age_7_9": "吃饭时聊聊：今天有没有遇到不懂的事情？比如作业里的生词、朋友说的新游戏。承认不知道后，你是怎么做的？",
                    "age_10_12": "提醒孩子：老子的智慧需要慢慢品。下次遇到难题，试着先说‘这个我不确定’，然后一起查资料或讨论。不急着下结论，智慧就在过程中。"
                }
            ],
            "parent_tips": "当孩子说‘我不知道’时，给他一个温暖的微笑。这句话不是终点，而是探索的起点。",
            "review_status": "approved",
            "reviewed_by": "",
            "reviewed_at": "2026-05-12",
            "review_history": [
                {
                    "action": "created",
                    "by": "extract_meta.py",
                    "at": "2026-05-12T00:00:00Z",
                    "notes": "AI generated - awaiting review"
                },
                {
                    "action": "reviewing",
                    "by": "admin",
                    "at": "2026-05-12T11:08:04.062Z",
                    "notes": ""
                },
                {
                    "action": "approved",
                    "by": "admin",
                    "at": "2026-05-12T11:09:00.838Z",
                    "notes": "何继杰"
                }
            ]
        },
        "78": {
            "chapter": 78,
            "title": "水之德",
            "core_idea": "水是最柔软的东西，却能穿透最坚硬的石头。因为它从不放弃，慢慢地、持续地努力。我们也可以像水一样，用耐心和温柔去面对困难，而不是硬碰硬。",
            "safety_notes": [
                "避免讨论‘洪水’或‘溺水’等可能引发恐惧的水的负面影响。",
                "不要将‘柔弱’曲解为‘懦弱’或‘放弃’，强调耐心和持续努力。",
                "避免用‘垢’和‘不祥’等词直接描述孩子，以免引发焦虑。"
            ],
            "interaction_points": [
                {
                    "topic": "像水一样坚持",
                    "age_4_6": "带孩子看水滴落在石头上的样子，或者用手指蘸水在石头上画圈，说：‘水慢慢滴，石头就变圆啦！’",
                    "age_7_9": "问孩子：‘你有没有像水一样，慢慢做一件事最后成功了？比如拼图、练字？’",
                    "age_10_12": "讨论：为什么水能穿石？‘慢’和‘坚持’哪个更重要？你能想到生活中的例子吗？"
                },
                {
                    "topic": "柔软的力量",
                    "age_4_6": "让孩子用手捏一块软海绵和一块硬积木，问：‘哪个更容易变形？水就像海绵一样柔软，却能洗掉脏东西。’",
                    "age_7_9": "问孩子：‘你见过妈妈用洗碗布轻轻擦掉油污吗？为什么用力反而不好？’",
                    "age_10_12": "讨论：为什么老子说‘弱之胜强’？你能想到历史上或身边‘以柔克刚’的例子吗？"
                },
                {
                    "topic": "把智慧带入生活",
                    "age_4_6": "洗澡时，让孩子观察水从指缝流走，说：‘水很温柔，但能把我们洗干净。’",
                    "age_7_9": "邀请孩子：‘今天我们遇到困难时，可以想想水会怎么做？’",
                    "age_10_12": "提醒孩子：‘水的智慧需要慢慢体会，不用着急，就像水滴石穿一样。’"
                }
            ],
            "parent_tips": "和孩子一起玩水的时候，可以轻轻说：‘水很温柔，但它很有力量。’不用讲道理，孩子会自己感受到。",
            "review_status": "approved",
            "reviewed_by": "",
            "reviewed_at": "2026-05-12",
            "review_history": [
                {
                    "action": "created",
                    "by": "extract_meta.py",
                    "at": "2026-05-12T00:00:00Z",
                    "notes": "AI generated - awaiting review"
                },
                {
                    "action": "reviewing",
                    "by": "admin",
                    "at": "2026-05-12T11:09:03.601Z",
                    "notes": ""
                },
                {
                    "action": "approved",
                    "by": "admin",
                    "at": "2026-05-12T11:19:16.119Z",
                    "notes": "何继杰"
                }
            ]
        },
        "81": {
            "chapter": 81,
            "title": "信言不美",
            "core_idea": "真正的好话可能不那么好听，就像苦瓜吃起来苦但对身体好；真正聪明的人不炫耀，就像大树悄悄长高；你越分享，快乐和友谊就越多，就像你分一半饼干给朋友，心里却甜甜的。",
            "safety_notes": [
                "避免让孩子觉得说实话就会挨批评，要强调真实的话是温暖的。",
                "避免用'不善良'、'没真本事'等词评价孩子或他人。",
                "避免让孩子误解'不争'就是什么都不做，要强调是做好事不抢功劳。",
                "避免用'分享会变富'暗示物质回报，要侧重情感和精神收获。"
            ],
            "interaction_points": [
                {
                    "topic": "好听的话vs真话",
                    "age_4_6": "和宝宝玩'真假话游戏'：你说一句好听的假话（比如'宝宝是超人'），和一句不好听的真话（比如'宝宝现在需要刷牙'），让宝宝指哪句是真的。然后学小猫咪'喵'一声表示喜欢真话。",
                    "age_7_9": "问孩子：有没有听过'好听的话'后来发现是假的？比如同学夸你新玩具好看，其实想玩？那真实的话虽然可能不好听，但为什么更重要？",
                    "age_10_12": "引导孩子思考：为什么老子说'信言不美'？可以举例子：医生说'你要多运动'不好听但有益，广告说'吃了就变聪明'好听但骗人。你遇到过类似情况吗？"
                },
                {
                    "topic": "分享的快乐",
                    "age_4_6": "和宝宝一起分水果：你给妈妈一块苹果，妈妈开心地笑了，宝宝也笑了。问宝宝：你给了苹果，但你的开心变多了吗？学小松鼠'吱吱'表示分享真快乐。",
                    "age_7_9": "问孩子：你借给朋友一本漫画书，朋友很开心，你失去书了吗？没有，你还可以看，而且朋友更愿意和你玩了。分享后你得到了什么？",
                    "age_10_12": "讨论：老子说'既以为人己愈有'，分享真的会让自己更富有吗？可以是友谊、信任、快乐。你分享过什么？得到了什么？"
                },
                {
                    "topic": "把智慧带入生活",
                    "age_4_6": "洗澡时，让宝宝把玩具分给小鸭子，说'分享让泡泡更多'。吃饭时，宝宝分一口菜给你，你夸他'你像小圣人'。",
                    "age_7_9": "今天家里有没有人说了'不好听的真话'？比如提醒你写作业。我们可以感谢他，因为真话帮助我们成长。",
                    "age_10_12": "这一章的道理很深，可以慢慢体会。下次遇到'好听的话'和'真话'时，想想老子的话。不急着改变，先观察。"
                }
            ],
            "parent_tips": "和孩子一起读时，可以轻轻地说：'有时候真话像柠檬，酸酸的但对身体好。' 不用急着讲道理，让孩子在故事和游戏中自己感受。",
            "review_status": "approved",
            "reviewed_by": "",
            "reviewed_at": "2026-05-12",
            "review_history": [
                {
                    "action": "created",
                    "by": "extract_meta.py",
                    "at": "2026-05-12T00:00:00Z",
                    "notes": "AI generated - awaiting review"
                },
                {
                    "action": "reviewing",
                    "by": "admin",
                    "at": "2026-05-12T11:19:19.394Z",
                    "notes": ""
                },
                {
                    "action": "approved",
                    "by": "admin",
                    "at": "2026-05-12T11:22:11.963Z",
                    "notes": "何继杰"
                }
            ]
        }
    },
    "_version": "1.1",
    "_updated": "2026-05-13"
}
